<?xml version="1.0"?>
<!DOCTYPE hibernate-mapping PUBLIC "-//Hibernate/Hibernate Mapping DTD 3.0//EN"
"http://hibernate.sourceforge.net/hibernate-mapping-3.0.dtd">
<!-- 
    Mapping file autogenerated by MyEclipse - Hibernate Tools
-->
<hibernate-mapping>
    <class name="com.iba.ehis.dobj.LcLaundryReceipts" table="LC_LAUNDRY_RECEIPTS" >
        <composite-id name="id" class="com.iba.ehis.dobj.LcLaundryReceiptsId">
            <key-property name="operatingFacilityId" type="java.lang.String">
                <column name="OPERATING_FACILITY_ID" length="2" />
            </key-property>
            <key-property name="receiptNum" type="java.lang.String">
                <column name="RECEIPT_NUM" length="10" />
            </key-property>
        </composite-id>
        <property name="linenItem" type="java.lang.String">
            <column name="LINEN_ITEM" length="20" not-null="true" />
        </property>
        <property name="receivedQty" type="java.lang.Long">
            <column name="RECEIVED_QTY" precision="6" scale="0" not-null="true" />
        </property>
        <property name="receivedDate" type="java.util.Date">
            <column name="RECEIVED_DATE" length="7" not-null="true" />
        </property>
        <property name="receivedBy" type="java.lang.String">
            <column name="RECEIVED_BY" length="30" not-null="true" />
        </property>
        <property name="remarks" type="java.lang.String">
            <column name="REMARKS" length="100" />
        </property>
        <property name="addedById" type="java.lang.String">
            <column name="ADDED_BY_ID" length="30" not-null="true" />
        </property>
        <property name="addedDate" type="java.util.Date">
            <column name="ADDED_DATE" length="7" not-null="true" />
        </property>
        <property name="addedFacilityId" type="java.lang.String">
            <column name="ADDED_FACILITY_ID" length="2" not-null="true" />
        </property>
        <property name="addedAtWsNo" type="java.lang.String">
            <column name="ADDED_AT_WS_NO" length="30" not-null="true" />
        </property>
        <property name="modifiedById" type="java.lang.String">
            <column name="MODIFIED_BY_ID" length="30" not-null="true" />
        </property>
        <property name="modifiedDate" type="java.util.Date">
            <column name="MODIFIED_DATE" length="7" not-null="true" />
        </property>
        <property name="modifiedFacilityId" type="java.lang.String">
            <column name="MODIFIED_FACILITY_ID" length="2" not-null="true" />
        </property>
        <property name="modifiedAtWsNo" type="java.lang.String">
            <column name="MODIFIED_AT_WS_NO" length="30" not-null="true" />
        </property>
    </class>
</hibernate-mapping>
