<?xml version="1.0" encoding="UTF-8" standalone="no"?>
<pk><wd nm="comply" rd="3136,0:999"/><wd nm="component" rd="253,0:66,162,344,487|291,0:295|306,0:356|323,0:515,546,643,663,704,729,748,3433,3456,4058,4150,4540,7041,8478,8499,8554,8579,8598,8617,8644,8723,8732,8752,8806,8835,8863,8887,8996,9014,9045,9068,9091,9110,9382,9431,9455,9495,9528,9608,9731,10014,10038,10097,10132,10162,10192,10246,12994,13163,13212,13239,13277,13301,13340,13413,13497,15132,16936,18677,18699,18854,18894,18980,19024|324,0:1758|472,0:347|473,0:1433|496,0:399|507,0:278|511,0:196,243|528,128:16,42,99,140,221,276,370,440,495,532,630,1027,1082,1220|530,0:269|532,0:206,360|546,0:285,1598|547,0:367|556,0:265,321,928|557,0:289,372,449,1121|559,0:855,896|565,0:2738,2792|604,0:603|622,0:3038,3092|624,0:613|625,0:141,154,235,354,707|626,0:364,391|633,0:168,188|634,0:80,96,287,308,453,701,714,776|635,0:175,188,643,717,788|636,0:219,265,283,312,350,475|637,0:251,264,373,393,406,513,567,629,688,745,835,952,1015|641,0:178,191,661,678,747|644,0:516|645,0:423,501|647,0:917,935,1044,1111|650,0:1002,1045|657,0:423|658,0:558|676,128:9,41,98,187,237,430,551,568,625,879,950,993,1533,1556,1789,1809,1833,1910,1922,1978,1991,2058,2098,2142,2224,2328,2346,2445,2728|677,128:9,37,121,153,219,341,392,663,745,784,1631,2146,2229,2284,2370,2479,2634|678,0:892,905,1394|683,0:1365|684,128:7,134|685,0:493,1970,1998,2043,2146,2189,2246,2302,2335,2360,2422,2469,2545,2713,2772,2854|688,0:421,1367|690,0:973|701,0:239,263,304|717,0:325|732,0:269|733,0:208,362|764,0:508|859,0:495,2732|862,0:588|874,0:131,267,291,332|894,0:97,165,239,323|896,0:310|934,0:121,261|935,0:169,248,268,369,1537,1732,2314,2381|939,0:64|941,0:568,651,1792|946,0:74,537,573,639,748|948,128:15,39,161,191,206,337,364,414,449,1042|959,128:5,20,58,82,309,348,374,516,766,833,1108,1166,1342|960,0:273|965,128:11,32,92,209,254,286,483,639|968,0:299|969,128:9,27,195,463,506,535,684,766,885|980,0:662,673,722,792,924,965,990|987,0:283|993,0:158,740,965,1079,1145|994,0:1108|1035,0:120,223|1038,0:1344|1052,0:58,574,647,720,764,862,2787,2900,2944,3056,3167,3303,3370,3457,3824|1053,0:840,956,1011|1057,0:56,69,229|1060,0:114,154|1061,0:168,564|1062,0:66,486,675,854|1081,0:2473,2520|1082,0:200,242|1083,0:185,682,931,940,992,1017,1099,1129,1328,1658,1827,2208,2543,2905,3068,3090|1107,0:162|1117,0:4894|1136,0:162|1195,0:162|1207,0:162|1210,0:79,130|1217,0:162|1223,0:53|1249,0:810,884,943,1169|1267,0:90|1272,0:409,447,4955,6065,12097|1275,0:78,128,356,432,845,3467|1276,0:12614,13092|1278,0:5992|1279,0:801|1291,0:867|1311,0:398|1314,0:389,586,1144,1274,1362,1413,1483|1445,0:1923,2028|1454,0:86,434,539,809,964,1127,1282,1868|1456,0:81,426,531,801,960,1116,1271,1799|1577,0:2407,2526,2611|1590,0:942,1061,1146|1606,0:2601,2620,2740,2825|1642,0:2157,2176,2296,2382|1654,0:2202,2221,2341,2427|1837,0:2200,2247|2001,0:360,797,816,841,1086,1103|2035,0:869,915,1880|2040,0:995,1024|2149,0:778|2191,0:424|2193,0:537|2199,0:672|2293,0:142|2347,0:7400,7466,17725,17971|2402,0:4744|2407,0:2961|2413,0:5370|2443,0:594|2461,0:1632|2551,0:1547,1816|2780,128:0,10,48,111,127,173,228,283,414,451,498,519,667,738,888|2783,0:270,288,335,374,397|2790,128:3,16,66,125,285,397,444,468,613,713,881,1001|2801,0:190|2832,0:68,181,419,543,615,737,784|2850,0:165,204,232,257,334,381|2950,0:72,341,400,468,621|2951,2:83,202,355,483,789,836,877,923,1146|2953,0:394,404,417,458,605,719,773,1002,1056,1368,1416,1501,1593,1757,1799|2964,0:47,64,87,224,269,388,614|2966,0:405,727,809,1376,1517,1722,2008|2967,0:579,2102,2292,2442,2577,2697,2746|2968,0:348,525,633,680,735|2970,0:688,829,1190|2971,0:1917,2106,2256,2391,2515,2564|2985,0:3666,4259|2986,0:3837,4430,5913|2988,0:3182,3442,4035,10752,11345|2989,0:1588,2236,2377|3000,0:115,547,606,650,1013,1048,1084|3032,0:713|3041,0:144|3073,0:2220|3094,1:19,82,384|3103,0:245|3117,0:4595|3119,0:2703|3126,0:5958|3128,0:1898|3132,0:2440|3143,0:4005|3193,0:114|3199,0:118|3650,0:2391,2564,2649|3655,0:917|3659,0:1065|4132,0:148|4266,0:784|4297,0:291|4341,0:1057,1123,1210,1275,1520,1538|4391,0:1408,1689,1733|4483,0:8635,10593|4556,0:444|4743,128:9,38,89,140,162,205,243,378,418,584,653,693,1001,1019,1202,1223,1425|4824,0:137|4825,0:192|4872,0:298|4874,0:533,570,584|4894,0:2510|4930,0:407|4953,0:1177,1243,1330,1395,1640,1658"/><wd nm="component’" rd="323,0:9646"/><wd nm="compos" rd="513,0:159|534,0:332|720,0:191|4742,0:161"/><wd nm="composite" rd="2940,0:424"/><wd nm="composition" rd="1755,0:190|1812,0:467|1815,0:481|1880,0:2208,2234,2324|1885,0:477|1886,0:761|1888,0:1817,1838,1946|1929,0:1859|2937,0:317,346,420|2939,128:16,48,96,228,315,354,396,426,500,574,731,863,895,936,979,1070,1113,1286,1528,1840|2940,128:0,11,50,80,120,135,564,583,614,629,655,679,706,731,753,892,1114|2941,128:0,16,60,90,121,141,170,193,250,285,333,365,390,417,561,641,771|2955,0:48,64,89,158,276|2957,0:49,65,89,153,271,354,413,451,482,501,643,701|2985,0:3530,3597,3614,3633,3730,3775,3798,3822,3852,3905,3924,3949,3976,4008,4077,4108,4202,4392,4469|2986,0:1940,3755,3901,3946,3969,3993,4023,4076,4095,4120,4147,4179,4248,4279,4373,4563,4640,5863,5930,5960,6020,6045,6072,6104,6166,6197,6333,6352,6394,7276|2988,0:3226,3286,3344,3506,3551,3574,3598,3628,3681,3700,3725,3752,3784,3853,3884,3978,4168,4245,5816,9217,10670,10816,10861,10884,10908,10938,10991,11010,11035,11062,11094,11163,11194,11288,11478,11555"/><wd nm="compound" rd="534,0:306|3116,0:429,1605|3124,0:1529|3128,1:50,66,238,336,354,376|3550,0:331,390,408,471,535|4266,0:612|4339,0:116|4342,0:5478,5511|4381,0:501|4397,0:3996,4024|4398,0:1534,1586,1645|4401,0:1138,1461|4407,0:1608,1642|4410,0:73,117|4422,0:800,834|4436,0:344,409|4437,0:347,412|4439,0:2675|4458,0:1836,1870|4459,0:1125,1609,1643|4466,0:5474,5508|4475,0:1748,1796"/><wd nm="comprehensiv" rd="1283,0:221|1295,0:142|1786,0:132|1808,0:106|2672,0:161|2673,0:194|3243,0:1170|4770,0:139"/><wd nm="compris" rd="103,0:240|532,0:527|733,0:529|2117,0:161|3243,0:339"/><wd nm="comprise" rd="89,0:568|92,0:894|93,0:833|253,0:451|323,0:13083|346,0:1000|535,0:281|736,0:297|1002,0:211|1486,0:195|1562,0:3967|2555,0:881|2713,0:292|2716,0:588|3121,0:190|3126,0:5241,5977|3183,0:4596|3242,0:156|3538,0:325|4752,0:242|4894,0:128"/><wd nm="comptroller" rd="3341,0:408"/><wd nm="compulsori" rd="288,0:136|324,0:1309|426,0:891|1072,0:2018|3119,0:569|4266,0:475,709|4398,0:729|4791,0:3029,3195"/><wd nm="compulsory" rd="91,0:87|1634,0:233|2404,0:5602"/><wd nm="comput" rd="39,0:268|146,0:159,234|264,0:536|404,0:3996,4213|420,0:3104,3446|778,0:623,681|1212,0:5030,5146|1320,0:611|1609,0:1373,1655|1632,0:10662|1662,0:2755|1723,0:1182,2354,2792|1724,0:1144,1293,2468,2906|1735,128:0,30,81,201,247,544,629,669,781,800,892,908,948,1563,1886|1736,128:0,30,81,169,215,466,540,580,692,710,791,807,846,1658,1976|1818,0:1203,1551,1779,1959|1819,0:50,1065,1412,1644,1824|1829,0:1466,1814,2016,2250|1830,0:1060,1411,1618,1860|1880,0:2981|1888,0:2551|1894,0:290|1899,0:2444|1909,0:376|1911,0:674|1913,0:957|2035,0:1823|2191,0:3033,3050|2193,0:1052|2194,0:940|2973,0:4197,4832|2986,0:11136,11771|2988,0:7080,7160|3051,0:2196|3093,0:394,530|3126,0:830,887|3136,0:2141|3181,0:360,695,879|3271,0:486|3279,0:414|3311,0:1183,3191,3597,3925,7499,7544|3315,0:417|3318,0:402,436,483,580|3321,0:2224,2379|3324,0:417,2079,2563,2658,3246,3705|3344,0:461|3346,0:333,2114|3433,0:494|3434,0:376|3470,128:0,23,221,328,615,761,2211,2262,2296,2486,2558,2702,2946,3009,3192,3358|3506,0:1484|3524,0:1148|3527,0:22646,37170,42301,42566,42773,51864,52160,52243,52439,52545,52769,52887,53059,53160,57248,57330,59697,59832,60060,60220|3533,0:2089,2618,2869|3552,0:8383,8758,9129,9507,9892|3554,0:2532,2709|3555,0:1431,3430,5336|3556,0:559,855,938,1134,1240,1464,1582,1754,1855,2518,4251|3557,0:1003,1231,1282|3562,0:6324,6549,6770,6998,7233|3571,0:5092,5341,5592,5877,6141|3572,0:5747,5991,6236,6516,6775|3573,0:1391|3575,0:5186,5433,5676,5926,6195|3576,0:2652,3899|3615,0:908,1125,1192,1531,1746,1813,2616|3623,0:1556|3624,0:2245,2539|3629,0:1421,1502,2475,2556|3630,0:2380|3632,0:255,2744,3367|3642,0:2546,7103,7328,7549,7777,8012|3643,0:449,1861|3666,0:4289|3679,0:760|3681,0:626|3697,0:3571|3720,0:2157,2210,2275,9431,9484,9549|3791,0:597|3811,0:583,626,984,1022|3812,0:605,910,2306,2471|3825,0:1950,2474|3830,0:941,995,1094|3832,0:261,294,1406,1515,2748|3834,0:270,303,1406,1515,2671|3843,0:272,305,1408,1517,2673|3844,0:718,1978|3848,0:2043,2567|3857,0:262,295,1404,1513,2746|3859,0:267,300,1409,1518,2674|3872,0:4874|3874,0:1144|3966,0:380|3969,0:348|3988,0:1912|3990,0:149,672|4000,128:0,17,56,188,221,469,575,794,923,986,1014,1094,1229,1424,1519,1675|4004,0:452,882|4005,0:921|4006,0:1117|4008,0:1595|4017,0:1227|4018,0:1294|4049,0:719|4050,0:1038|4066,0:438|4072,0:112|4077,0:412|4080,0:3573|4087,0:3549|4090,0:896|4100,0:1483|4111,0:701|4114,0:797|4124,0:1152,1392,1532,1690|4138,0:413|4150,0:574,890,1288,1454,2004,2147|4327,0:723,1090|4329,0:5163,5530|4391,0:1386|4671,0:230,263,1511,1620,2101|4790,0:1244|4936,0:505"/><wd nm="computation" rd="1842,0:5419|3289,0:545|3340,0:446|3344,0:497,528,572|3470,0:449,674,1780,1885,2918|3506,0:1599|3527,0:41741,42949,43020,43168,43202,60376|3533,0:1597,1686,1780,1887,1934,2156,3052,3141|3624,0:530,1976,4485,4516,4597|3811,0:902|3988,0:1809,1971|3990,0:733|4000,0:300,707,834,1270|4035,0:1378|4150,0:2106"/><wd nm="compute" rd="1721,0:2613|1735,0:328|1736,0:287|3470,0:1468|3812,0:731,939,1147,1993,2217|3844,0:804,2073|4391,0:958,1135"/><wd nm="computer" rd="563,0:143|570,0:294|577,0:495|723,0:518|1318,0:81,202,525|1471,0:557|1780,0:83|2043,0:233|2044,0:2103|2045,0:248|2046,0:632|2193,0:275|4917,0:83|4943,0:168"/><wd nm="con" rd="142,128:0,1412|181,0:1136|218,128:3,890|219,128:8,1143|222,128:5,754|1240,0:4564|1244,0:3490|1917,0:1374,1430"/><wd nm="concatenat" rd="1888,0:1211|1899,0:1226"/><wd nm="concatenation" rd="810,0:2355|2529,0:220"/><wd nm="conceiv" rd="1152,0:1464,1655|1155,0:53|1157,0:1462,1653|1167,0:1450,1641|1185,0:1477,1668|1626,0:584|2404,0:1655"/><wd nm="concentration" rd="1977,0:246|2054,0:2136,2169|2100,0:2861|4367,0:873,923,1000,1139,1187,1266|4388,0:445,474"/><wd nm="concept" rd="1689,0:1574|3127,0:688|3576,0:3031|4135,0:1522"/><wd nm="concern" rd="2054,0:1027|2098,0:784|2110,0:4394|2148,0:898|2271,0:281|2273,0:332|2476,0:398|3475,0:906,2412|3819,0:1912|3822,0:939|3846,0:836|3946,0:604|3947,0:590|4216,0:238|4502,0:136,189"/></pk>