<?xml version="1.0"?>
<!DOCTYPE hibernate-mapping PUBLIC "-//Hibernate/Hibernate Mapping DTD 3.0//EN"
"http://hibernate.sourceforge.net/hibernate-mapping-3.0.dtd">
<!-- 
    Mapping file autogenerated by MyEclipse - Hibernate Tools
-->
<hibernate-mapping>
    <class name="com.iba.ehis.dobj.DsCommFormulaLang" table="DS_COMM_FORMULA_LANG">
        <composite-id name="id" class="com.iba.ehis.dobj.DsCommFormulaLangId">
            <key-property name="languageId" type="java.lang.String">
                <column name="LANGUAGE_ID" length="6" />
            </key-property>
            <key-property name="commFormulaCode" type="java.lang.String">
                <column name="COMM_FORMULA_CODE" length="60" />
            </key-property>
        </composite-id>
        <property name="longDesc" type="java.lang.String">
            <column name="LONG_DESC" length="180" not-null="true" />
        </property>
        <property name="shortDesc" type="java.lang.String">
            <column name="SHORT_DESC" length="90" not-null="true" />
        </property>
        <property name="addedById" type="java.lang.String">
            <column name="ADDED_BY_ID" length="90" />
        </property>
        <property name="addedDate" type="java.util.Date">
            <column name="ADDED_DATE" length="7" />
        </property>
        <property name="addedFacilityId" type="java.lang.String">
            <column name="ADDED_FACILITY_ID" length="6" />
        </property>
        <property name="addedAtWsNo" type="java.lang.String">
            <column name="ADDED_AT_WS_NO" length="90" />
        </property>
        <property name="modifiedById" type="java.lang.String">
            <column name="MODIFIED_BY_ID" length="90" />
        </property>
        <property name="modifiedDate" type="java.util.Date">
            <column name="MODIFIED_DATE" length="7" />
        </property>
        <property name="modifiedFacilityId" type="java.lang.String">
            <column name="MODIFIED_FACILITY_ID" length="6" />
        </property>
        <property name="modifiedAtWsNo" type="java.lang.String">
            <column name="MODIFIED_AT_WS_NO" length="90" />
        </property>
    </class>
</hibernate-mapping>
