<?xml version="1.0"?>
<!DOCTYPE hibernate-mapping PUBLIC "-//Hibernate/Hibernate Mapping DTD 3.0//EN"
"http://hibernate.sourceforge.net/hibernate-mapping-3.0.dtd">
<!-- 
    Mapping file autogenerated by MyEclipse - Hibernate Tools
-->
<hibernate-mapping>
    <class name="com.iba.ehis.dobj.DsRdaChart" table="DS_RDA_CHART" >
        <composite-id name="id" class="com.iba.ehis.dobj.DsRdaChartId">
            <key-many-to-one name="amAgeGroup" class="com.iba.ehis.dobj.AmAgeGroup">
                <column name="AGE_GROUP_CODE" length="2" />
            </key-many-to-one>
            <key-property name="heightRangeFrm" type="java.lang.Long">
                <column name="HEIGHT_RANGE_FRM" precision="22" scale="0" />
            </key-property>
            <key-property name="heightRangeTo" type="java.lang.Long">
                <column name="HEIGHT_RANGE_TO" precision="22" scale="0" />
            </key-property>
            <key-property name="weightRangeFrom" type="java.lang.Long">
                <column name="WEIGHT_RANGE_FROM" precision="3" scale="0" />
            </key-property>
            <key-property name="weightRangeTo" type="java.lang.Long">
                <column name="WEIGHT_RANGE_TO" precision="3" scale="0" />
            </key-property>
        </composite-id>
        <property name="serial" type="java.lang.Long">
            <column name="SERIAL" precision="22" scale="0" />
        </property>
        <property name="energyAllowance" type="java.lang.Long">
            <column name="ENERGY_ALLOWANCE" precision="22" scale="0" />
        </property>
        <property name="pregAddtionalEnerAllowance" type="java.lang.Long">
            <column name="PREG_ADDTIONAL_ENER_ALLOWANCE" precision="22" scale="0" />
        </property>
        <property name="lactAddtionalEnerAllowance" type="java.lang.Long">
            <column name="LACT_ADDTIONAL_ENER_ALLOWANCE" precision="22" scale="0" />
        </property>
        <property name="effStatus" type="java.lang.String">
            <column name="EFF_STATUS" length="1" />
        </property>
        <property name="addedById" type="java.lang.String">
            <column name="ADDED_BY_ID" length="30" />
        </property>
        <property name="addedDate" type="java.util.Date">
            <column name="ADDED_DATE" length="7" />
        </property>
        <property name="addedFacilityId" type="java.lang.String">
            <column name="ADDED_FACILITY_ID" length="2" />
        </property>
        <property name="addedAtWsNo" type="java.lang.String">
            <column name="ADDED_AT_WS_NO" length="30" />
        </property>
        <property name="modifiedById" type="java.lang.String">
            <column name="MODIFIED_BY_ID" length="30" />
        </property>
        <property name="modifiedDate" type="java.util.Date">
            <column name="MODIFIED_DATE" length="7" />
        </property>
        <property name="modifiedFacilityId" type="java.lang.String">
            <column name="MODIFIED_FACILITY_ID" length="2" />
        </property>
        <property name="modifiedAtWsNo" type="java.lang.String">
            <column name="MODIFIED_AT_WS_NO" length="30" />
        </property>
    </class>
</hibernate-mapping>
