<?xml version="1.0" encoding="UTF-8" standalone="no"?>
<pk><wd nm="curser" rd="679,0:1890"/><wd nm="cursor" rd="143,0:972,1107|144,0:1124,1265|148,0:1069,1210|149,0:1068,1209|650,0:699|655,0:464,536|678,0:1211,1333,1380|679,0:1378,1500,1547,1825|807,0:7176|1269,0:936|1296,0:3377,12303|1298,0:1589,1757|1316,0:1481|2175,0:630|2490,0:1046|2776,0:357|2892,0:665|2952,0:1238,1801,2616|2953,0:965,1220|3010,0:2136,2228,4049|3012,0:403|3069,0:139,515|3209,0:5132,5199|4598,0:839,1086|4603,0:211|4622,0:5199"/><wd nm="curve" rd="1292,0:10213"/><wd nm="cus" rd="184,0:1353|3785,0:902"/><wd nm="cusp" rd="3043,0:1906|3056,0:3521,3674|3058,0:2350|3064,0:7724|3073,0:5164"/><wd nm="cust" rd="139,128:0,1021|140,128:0,1838|142,128:18,1380|154,0:63,487|201,128:16,1452|229,128:0,844|1737,0:2341,2417|1738,0:827,903|1741,0:640,716|1742,0:254|3434,0:1047|3627,0:34594,34658|3648,0:207,352|3681,0:281,370|3733,0:612,661,750,810,891,1041,1238|3767,0:172,229|3769,0:118,238|3801,0:3211|3803,0:96|3807,0:3561|3817,0:2627|3818,0:2493|3820,0:3037|3828,0:103|3869,0:1952|3897,0:241,360|3941,0:3861|3942,0:2374|3965,0:2967|3978,0:564,631|4031,0:2154,2637|4032,0:4667,5313|4037,0:5830,6313,8054,8432,10155|4039,0:1596|4060,128:0,1584|4255,0:567,633|4263,0:1374,1441,4615,4661"/><wd nm="custody" rd="2433,0:669|4747,0:145"/><wd nm="custom" rd="41,0:936|976,0:283|1008,0:431|1076,0:6068|1142,0:591,1078,1105|1295,0:4193|2563,0:812,844,906,994|2568,0:428|2586,0:887,919,981,1069|2601,0:5530|2713,0:635|2730,131:19,48,103,323,357,448,489,827,951,1049,1217|2814,0:330,393|3212,0:335|3990,0:303|3991,0:331"/><wd nm="customer" rd="41,0:721|112,0:540,559|113,0:99,189,282,601,795|115,0:549,563,609,987,1070,1320|117,131:0,8,46,73,99,135,177,239,285,325,371,428,457,481,780,797,857,892,916,939,959,993,1039,1098,1355,1403,1439,1459,1582,1656,1697,1728,1756,1932,1974,2006,2035,2273,2796,2826,2926,3011,3164,3250,3397,3498,3640,3737,4578,4783,4963,5078,5505,5568,5745,5901,6077,6182,6358|118,131:0,27,92,135,177,241,300,432,468,507,598,685,754,767,802,852,887,1155|119,131:0,13,56,82,132,163,218,230,265,313,375,668,681,697,784,807,848,873,1012,1122,1297|120,131:0,12,54,79,150,180,234,284,351,432,467,513,524,720,760,784,924,1034,1182|121,0:78,191,412,470,486,545,564|122,0:81,131,240,497,566|124,0:247,276,366|126,0:219,310,406|127,0:130,766|128,0:102,317,501|129,0:228,475,525,978|130,0:237,522|136,0:543|137,131:13,35,104,166,318,412,441,492,544,578,677,714,743,1007|138,0:200,616,898|139,3:11,73,99,170,321,413,474,509,541,584,611,690,792,849|140,3:9,123,135,195,572,620,652,858,942,990,1033,1183,1480,1531|141,0:1302,1476,1527|142,3:45,117,152,208,407,532,591,634,726,817,870,919,975,1044,1092,1170|143,0:241|144,0:552,743|145,0:90,550,735|147,0:82,533,715|148,0:512,694|149,0:514,695|150,0:1148,1173,1200,1304,1365,1398,1503,1571,1732,1882,2066|153,0:49,62,83,146,211,240,417,497,608,797,913,1696,1989,2160,2204,2242,2343,2383,2465,2495,2527,2591,2901|154,0:46,85,153,276,405,545,832,976,1054|155,0:52,69,90,157,279,407|156,0:564|157,0:492|158,0:263,276,1356,1376|159,0:74,95,193,208,229,280,293,448,558,772,1450,1691,1858|160,0:559,588,690,715,731,777,797,872,962,1008,1034,3068|165,0:929,1044,1078,1430,1494,1536,1605,1678,2165,2313,2561,2606,2616,4613|166,0:314,357,373,399,715,1005,1269,1874|167,0:70,83,125,444|168,0:115,129,159,192,550,575|171,0:636,653,734,767,788,856,920,1446,1488,1512,2017,2062,2072,3983,6731|173,0:639,656,737,770,791,859,923,1461,1503,1527,2024,2069,2079,3967|177,0:830|178,0:630,647,728,761,782,850,935,976,1189,1234,1244,2515|179,0:81,119,200,233,254,322,418|181,0:67,105,191,224,250,319,415,1884,2529|182,0:670,687,768,801,822,890|184,0:318,343,374,1369,1396|185,0:66,117,664,763|186,0:194,215,331|187,0:1082|189,0:339,360,401,429,1011,2112|192,0:689|193,0:114,163,237,297,391,437,521,1619|194,0:77,119,139,176|197,0:100|198,0:80,203,280|201,3:44,95,191,335,415,554,607,672,716,968,1053|202,0:189|204,0:96|206,0:98|207,0:77,161|211,0:95|212,0:72,155|216,0:88|217,0:115,342,653,734,767,788,856,952,1385|218,0:80,185,265|220,0:110,211|221,0:80,175,315|223,0:108,227|224,0:80|225,0:138,307,538,971,1052|228,0:92|229,3:14,105,142,218,241,299,331|230,0:90|231,0:80,188,521,848|234,131:0,16,93,451,520,581,612,947,1099|236,0:152,205,350|239,0:92,203,712,732,769|240,0:94,168,344,788,904,950|241,0:202,325,1453|242,0:255,572,620|243,0:125,193,316,790,810,847,996,2334,2907,4260,4612|425,0:1962,2001,2068,2102,3326|426,0:507,640|571,0:588|1646,0:4219,4258,4325,4359,4527,7377,7416,7483,7517,7685|1717,0:132,144,265,326,340,372,386,474,483,980,989|1718,0:134,146,278,292,855,864|1721,0:543,562,750,769|1722,0:510,529,713,732|1724,0:576,590,3284,3295|1726,0:111,262,331|1727,0:7039,7048,12471|1734,0:98,145,161,245,287,298,328,396,505,635,654,1458,1500,1516,1600,1642,1653,1746,1776,1943,1962|1735,0:104,151,167,251,293,304,334,402,512,640,659,1170,1212,1228,1316,1358,1369,1462,1492,1661,1680|1737,0:2354,2454,2667|1738,0:840,940,1153|1741,0:653,755|1742,0:263|1745,0:455|1746,0:715,757,779,909,1011,1037,1079,1180,1377,1522,2303,2312|1747,0:202,250,290,645,1014,1082|1748,0:359,720|1760,0:4969|2441,0:353|2532,0:565,642|3335,0:1240,1254|3354,0:745|3356,0:218,352|3369,0:319|3370,0:105,338|3371,0:90,542|3372,0:111,490|3374,0:168,413,499,990,1035|3378,0:441|3379,3:13,48,194,325,413,481,573,631,716,763,1336,1360,1438,1489,1530,1627,1699|3380,0:205|3382,0:1113|3385,0:368,931|3391,0:315|3392,0:95,172,369,455,502,519,980,1010,1159,1228|3393,0:88,107,276,290,388,402,477,554|3425,0:308|3427,0:97,438,1646,1980,3891,3926,3995,4054,4144,4191,4233,4321,4454,4538,4649,4702,4746,4786,4827,4997,5111,5230,5342,5708,5880,8563,8593,8631,8698,8993|3432,0:119,302|3433,0:258,424|3439,0:115,187,261,902,2757,2796|3440,0:313,648|3442,0:101,231,371,764,789,847,911,995,1007,1046,1078,1131,1226,1250,1283,1419,1464,1540,1585,3148,3187|3507,0:541|3510,0:1022|3513,0:130|3533,0:286,346,413,439|3536,0:132|3537,0:112,251,320,387,966,2252,2449,2666,3014,3198,3230,3260|3539,0:119,248,422|3540,0:189|3542,0:158,485,588|3543,0:163,482,585|3544,0:1655|3545,0:110,277,337|3547,0:268,294,365|3548,0:259,285,356|3553,0:107,205,276,348,381|3554,0:125|3556,0:124,250,390|3558,0:113,203|3560,0:1640|3562,0:139,239,671,2491,2608,2640,2670|3564,0:98,198|3565,0:123,202,593|3573,0:81,163,569,593,661,726|3574,0:165,486,584,681,1396,1414,1439,1452|3581,0:865,924,1198,1234|3596,131:10,28,84,132,205,246,309,331,373,437,2067|3627,0:468,13975,34467,34483,34607,34670|3632,0:675|3643,0:2659,2753,2924,3048|3646,0:13,60,102,117,143|3648,0:227,255,294,369,392,428,468,587,1867,1885,2021,2039|3652,0:457,543,711,726,771|3653,0:506,1225,1478,1493,1509,2795,2826,2871,2927,3561,3929|3661,0:166,319,406,689,726,762,848,953,1550,1828,5341,5432|3662,0:190,231,369,392,462,623,768,823,912,967,1598,2454|3673,1:43,71,123,365,405,454,591,659,1341,1528,4591,4603,4679,4765,4936,4975,5412,5799,6045,6293,6574,6835|3674,0:2483,4275,4325,4387,4430|3677,0:2983,3175,3221,3388,3622,3881|3681,0:96,243,270,293,387,419,494,871,1011|3682,0:78,273,284,330,430,465,476,492,542,562,589,615,647,670,886,895,1256,1265,1806,1863|3699,0:77,119,165,259,287,324,370,464,7875,7889,7939,7950,8746,8760,8810,8821|3702,0:855|3710,0:1507,1586|3728,0:1090,1138,1241,1284|3731,0:963,1080|3732,0:629,675,921,964|3733,0:643,704,763,795,850,1250|3740,0:349|3742,0:332,378|3745,0:198,760,822,833,975,988,1031,1106,1557,1716|3748,0:799,1115,1429,1455,1476,1608|3749,0:406,723,1000,1026,1047,1179|3750,0:1047,1577,2367|3751,0:1220|3752,0:458,538,684|3755,0:2669|3756,0:655,1034,1135|3757,0:308,627,2233,3224,3733,4244,5412,6357,6846,7347|3760,0:471|3767,0:214,268,355|3768,0:1311,1513,1528,2932,3105,3182|3769,0:104,162,181,224,277|3785,0:918,945|3793,0:3930,4061,4100,4129|3795,0:435,449,993,1034,1048|3796,0:452,466,1011,1052,1066|3797,0:1378,1392,1429,1445|3798,0:1761,1775,1812,1828|3799,0:942,956,968,982,1142,1156,1181,1195|3800,0:144,263,295,325|3801,0:214,253,309,520,767,1184,1353,1477,1604,1750,3099,3127,3223,3715,4038,5677|3803,0:134,174,232,318,355,395,431,495,916,930|3804,0:560,569|3807,0:356,395,451,662,909,1326,1473,1596,1723,1843,1964,2116,3449,3477,3573,4065,4388,6296|3810,0:73|3811,0:85,124,157,230|3812,0:704|3813,0:503|3814,0:328,543|3815,0:389,432,499,547|3816,0:383,426,482,3085|3817,0:346,385,441,652,1132,1301,1425,1552,1708,2639,3203,4824|3818,0:345,384,440,651,1131,1297,1418,1574,2505,3069,4690|3819,0:369,609,1141,2795|3820,0:215,254,310,521,768,1185,1351,1472,3049,3613,3936,5388,5416,5724|3821,0:172,398|3823,0:699,894,3203,4134,4376,5170,5426,7185,7247,7304,7391,7622,7754,7924,7956,7986,10841,11772,12014,12808,13064|3825,0:179,294|3826,0:233,256,295,396,560,671|3827,0:548,815,1282,1509,1653,1682,3569,3838,7283,8014,9673|3828,0:143,181,231,270,303|3831,0:265,602,865,1157,1620,1736,1760,1789,1853,2072,2686,2757|3832,0:539,1049,1117,1134,1356,1393,1423,1515,1953,2384|3833,0:516,1012,1078,1095,1315,1352,1382,1474,1912,2341|3834,0:520,1039,1110,1127,1352,1389,1419,1511,1949,2384|3836,0:506,987,1046,1063,1276,1313,1343,1435,1873,2109|3837,0:426,896,955,972,1185,1222,1252,1344,1782,2018|3838,0:478,942,997,1014,1315,1352,1382,1470,1900,2775|3839,0:1364|3840,0:672|3841,0:42,65,100,246,268,302|3866,0:842,1028|3867,0:487,653,777,904,1160,1197,1227,1252|3868,0:360,526,650,777,1068,1105,1135,1160|3869,0:252,585,751,875,1002,1282,1319,1349,1374,1964,2528,4318|3872,0:152,319|3874,0:1368,3527,4782,5323|3875,0:896,1130,1352,1565,1788,2021,2245,2464,2806,3040,3262,3475,3698,3931,4155,4374|3889,0:1116|3896,0:623,652,696,749,804,2091,2217|3897,0:278,340,389,457,727,1339|3898,0:459,512,566,1071,1368|3899,0:124,165,202,268,301|3901,0:929,982,1031|3904,0:639,692,785,2044,2059,2092|3912,0:500,521,572,652,692,739,755,801,875,910|3913,0:291,925,952,1267,1283,1326,1365,1391,1825,2599|3914,0:287,934,961,1281,1297,1338,1391,1417,1862,2636|3917,0:227,821,846,1156,1172,1213,1319,1731,2867|3918,0:260,877,904,1216,1232,1273,1379,1793,2734|3919,0:341,943,970,1272,1288,1331,1370,1396,1842,2804|3921,0:1361,1422,1462|3922,0:91,131,146,172|3923,0:616,1648,1662,1775,1816,1869,3516,3564,3598|3924,0:1240,3987,9017,9922|3925,0:1427,4256,9479,10367|3926,0:651,665,778,819,872,3536,4684,4732,4766|3928,0:1114,1866,2836|3939,0:516,1662,1674,1805,1853,1925,2039,4479,4519,4548,4695,5644,6093,6126,6337,6374,6393|3940,0:248,429|3941,0:528,2620,2632,2763,2811,2883,2997,3901,3930,4076,5037,5475,5504,5715,5752,5771|3942,0:526,1132,1144,1275,1323,1395,1509,2414,2443,2589,3546,4643,4672,4883,4920,4939|3950,0:649,692,714,767,1912,1960,1994,4216|3964,0:572,1837,1849,1980,2028,2100,2214,3078,3118,3147,3293,4242,5350,5383,5594,5631,5650|3965,0:529,1675,1687,1818,1866,1938,2052,3007,3036,3182,4139,4979,5008,5819,5856,5875|3978,0:579,643,967,984|3980,0:1290,1306|3983,0:81,118,157,1417,1644,2146|3999,0:372|4007,0:355,403|4008,0:378,426|4009,0:368,416|4018,0:114,266|4019,0:358|4022,0:1541|4023,0:606|4031,0:2166,2672|4032,0:4679,5348|4037,0:5842,6348,8066,8467,10194,10346,10367|4039,0:1608,1862,1890|4041,0:441|4054,0:685|4055,0:670|4056,0:82,309,390|4058,0:220|4059,0:110,137,232,347,443,505|4060,3:25,177,255,394,492,594,643,744,765,935,1052|4062,0:1011,2508,2628|4063,0:491|4067,0:734|4074,0:942,957|4075,0:813,828,3913,3930,4109,4125|4076,0:261,275|4078,0:1287|4080,0:1151|4081,0:398|4082,0:355|4083,0:471|4084,0:359|4094,0:512|4095,129:21,50,196,295,423,471,3608|4096,0:1768|4111,0:733,745,775,864|4116,0:1062|4129,0:1851|4131,0:1131|4146,0:510|4156,0:755,767,797,886|4168,0:108|4169,0:115,367|4172,0:132,228|4177,0:1303,1344,1372|4180,0:646,788,828,884,3102,3126,3287,3348,3374,3496|4191,0:2717,2760,2849|4195,0:726,868,908,964|4200,0:2756,2799,2888|4206,0:192,206|4207,0:750,766|4211,0:345,361,880,897,945,957|4215,0:66,89,144,162|4218,0:1842|4220,0:80,550,561,619|4222,0:1030|4225,0:1301|4226,0:1627,1687,2061,2284,2300|4231,0:90,121,149,175|4232,0:225,242,290,299|4237,0:306,363,425,452,473,505,518,536,566,764,778,2077,2091|4244,0:689,909|4254,0:549,746|4255,0:582,645|4263,0:1391,1465,2851,2968,4643,4701|4274,0:357,518,1445,4522,4645,6777,6983,7127,7166,7205,7231,7265,7276,7309,7360,7509,7525,7851,7867,8603,8621,8647,8735,8786,8825,8864,8890,8924,8935,8968,9019,9246,9260|4277,0:561|4282,0:504,523,657,676|4287,0:962,978,1232,1248|4292,0:1143|4468,0:1468,1557,1589,1667,1679,1702,1750,1802,2518,2607,2628,2675,2790,2806,2843,2859,2917,2938,2986,3089|5160,0:442|5165,0:360|5173,0:156"/></pk>