<?xml version="1.0" encoding="UTF-8" standalone="no"?>
<pk><wd nm="min’" rd="1637,0:1020"/><wd nm="mis" rd="383,0:392|397,0:433|567,0:4694,4744|624,0:5292|681,0:1661,3027|688,0:572|1648,0:1153|1667,0:220|2767,0:236|3012,0:5079,5128|3042,0:756|3048,0:2061|3052,0:1230|3056,0:609|3057,0:2909|3064,0:2322,2711,5598,5615|3071,0:565,2601|3073,0:5325|5047,0:627|5080,0:184"/><wd nm="misc" rd="153,0:2491|168,0:106,623|178,0:931|1550,0:453|1551,0:503|1552,0:501|3500,128:12,1215|3627,0:3606,3910|3680,0:5244|3686,0:11485,11677|3699,0:4564,4993,8457|3766,0:7389"/><wd nm="miscarriag" rd="1199,0:199,366"/><wd nm="miscellaneou" rd="117,0:903,926|140,0:1518|141,0:1514|153,0:2393,2537|165,0:1617|168,0:225|171,0:932,1433,1499|173,0:935,1448,1514|178,0:1040|185,0:53,1007|231,0:835|303,0:707|2063,0:632|2064,0:395|2065,0:308|2067,0:434|2068,0:269|2069,0:343|2071,0:284|2072,0:385|2112,0:2428,9184|2153,0:2550,9322|2473,0:1963|2905,0:6998|3113,0:256|3159,0:3505|3163,0:303|3166,0:676|3178,0:567,1543|3185,0:201|3194,0:774|3253,0:1080|3375,0:574|3396,0:566|3500,3:31,95,151,206,443,516,561|3570,0:1096|3575,0:1989,2251,2407,2505,2789,2945|3627,0:3660,3818,3963,4119,21192,21238,21278,22511,30619,31172,32383,32579,41702|3636,0:226,318,425,602,696,751,802,907,972,1141,1858,1929,2020,2582,2704,2846,2978,3143,3343,3521|3674,0:4976|3680,0:5310,5463|3686,0:11548,11739|3699,0:4533,4627,5055,8522|3700,0:475,957,977,1026|3712,0:593|3735,0:457,755,775|3748,0:871,1979,2003|3749,0:478,1542,1566|3766,0:7476,7752|3782,0:1404|3792,0:747,1241,1722,2040|3861,0:1221|3890,0:2249|3924,0:1298,1409,6136,6634|3925,0:1485,1596,5832,6363,7051|3936,0:2929,3039|3950,0:7677"/><wd nm="mishappen" rd="4293,0:258"/><wd nm="mismatch" rd="198,0:346|624,0:5342|681,0:2965,3061|694,0:760|695,0:4442|849,0:1535,2025|887,0:803|3486,0:367|5165,0:3762"/><wd nm="misplac" rd="4895,0:206"/><wd nm="mistak" rd="1145,0:2172|1301,0:5228|1304,0:4100|1318,0:295,2199|1462,0:5062|1655,0:2576|1677,0:160|2231,0:221|2752,0:314,2423|2753,0:3964"/><wd nm="mistake" rd="1137,0:1741|1153,0:1703|1212,0:1369|1224,0:1699|1235,0:1367"/><wd nm="mix" rd="1295,0:3840|3018,0:479,662|3034,0:536,604,625,827,1037,1142,1306,1390,3228,3569,3982,4250,4408,5170,5226,5301,5346,5421,5702,5805,5884,6299,6414|3061,0:598,622|3064,0:5064|3073,0:1134,1259,2444,2569,2851,3196,3499,3783,4065|3202,0:1300|4543,0:1366|4611,0:5896,6381,7270|4631,0:90"/><wd nm="mixtur" rd="3214,0:119,415|4611,0:7503,7873,8136|4631,0:219"/><wd nm="mixture" rd="536,0:319|3212,0:145,284,5369"/><wd nm="mkup" rd="171,0:3107"/><wd nm="ml" rd="89,0:73|99,0:2101|353,0:1526|513,0:924,987,1036|514,0:332,393,456,505|673,0:293|702,0:238|861,0:774,1188|876,0:219|1188,0:10531|1298,0:2965|1384,0:4501|2405,0:14314,14616|2419,0:748|2905,0:12765|3208,0:3913|3288,0:2959|3291,0:1573|4492,0:6664,7699,7928|4555,0:700,934,1062,1169|4887,0:3846"/><wd nm="mlc" rd="52,0:918|70,0:1602|92,0:2250,2328,2906,2921,2972,3043,3101,3123,3151,3231,3324,3367,3572,3765,3815,3953,4002,4049,4296,4346,4395,4426,4517,4570,4639,4725,4748|355,0:8152,8212,8228,8236,8312,8320,8350,8414,8431,8439,8515,8523|1129,0:641|1146,0:1417|1228,0:3336,3349,3401,3521,3675|1267,0:382|1649,0:2127,2140|1654,0:2310|2492,3:11,19,33,41,107,117,179,189,280,289,367,376,422,430,456,464,622,630,837,873,914,953,1030,1112,1121,1412|2588,3:13,34,216,271,318,350,629|2601,0:4367|2602,0:1801,1821,1885,1904,1951,1990,2023|2632,0:78|2651,128:18,1283|2652,128:18,205,607,749,901|2673,0:5263,5276,5360,7470|2744,135:9,25,107,285,430,509,558,587,725,2269,2369,2437,2519,2600,2751,2799,2930|2749,0:518|2751,0:185|2794,0:2161,3716,5185,5205|2800,0:3140,3546,5074,6338,6570|3301,0:728|3304,0:1390"/><wd nm="mlc/non-mlc" rd="2492,128:1782"/><wd nm="mlc/oscc" rd="2588,128:816"/><wd nm="mlmoh" rd="2091,0:3510"/><wd nm="mm" rd="27,0:473|32,0:840|35,0:622|39,0:242|40,0:2455|64,0:476|66,0:445|67,0:649|68,0:415,480,793,1029|71,0:1797|73,0:146|91,0:3324|92,0:1028,9213|95,0:616|96,0:980|97,0:126|98,0:3159|150,0:125|160,0:411,1275,1448,1705,3214|161,0:352,1252|165,0:491|168,0:1238|171,0:466,1167|173,0:469,1177,6111|178,0:506,2819,5849|179,0:716|180,0:117,584|181,0:697,1548|182,0:1296|189,0:1338|225,0:819|279,0:860,1017|325,0:2095,7046,11994,15417|341,0:1282|378,0:741,936|396,0:1316|400,0:503|409,0:1456|410,0:1259|411,0:184,333|412,0:710|413,0:563|415,0:2822|416,0:308|417,0:1250|418,0:662,1159|419,0:133|422,0:1232|423,0:720|427,0:2974,4775|429,0:766|430,0:1134|431,0:1604,4638|433,0:1109|436,0:863|438,0:594|441,0:135|442,0:1963|443,0:473|446,0:1123|447,0:2587,2666|450,0:751|452,0:3929,3941|453,0:549|697,0:4375|807,0:5255|1081,0:634,750|1113,0:450|1114,0:587|1123,0:3630|1126,0:280,465|1128,0:104|1130,0:429,494,821,1048|1131,0:1541|1136,0:748|1146,0:415,1051,2488,2831|1151,0:748|1157,0:733|1170,0:162|1185,0:1371,1420|1203,0:1023|1204,0:231|1210,0:743|1213,0:839,1409|1215,0:750|1222,0:740|1225,0:450|1228,0:4434|1232,0:742|1237,0:273|1240,0:627|1253,0:841|1255,0:1028|1258,0:3610,4086,4292,5068|1261,0:1066|1262,0:2620,3005,3239|1263,0:1176|1266,0:814|1271,0:1110,3412|1272,0:1051|1284,0:820|1292,0:9844,9898|1298,0:4458|1308,0:1034|1317,0:751|1322,0:675|1336,0:1021|1433,0:2527|1472,0:838,1207|1473,0:2615|1485,0:2877|1579,0:198|1609,0:666|1610,0:179|1613,0:518,615|1614,0:467,505,992,1030|1615,0:206,841|1616,0:660|1617,0:217,862|1619,0:185|1620,0:180|1621,0:524|1622,0:519,556|1623,0:202|1624,0:533,754|1625,0:215|1626,0:339,749|1627,0:185|1628,0:192,579|1629,0:343|1630,0:219|1631,0:200,618|1636,0:2406,3433|1637,0:1571,3191,3606|1638,0:1018,1185|1639,0:1855,2363|1640,0:302|1642,0:1123|1643,0:634|1644,0:4031|1650,0:304|1654,0:462,1941,3364,3850|1658,0:643,1042,2292|1659,0:733,2471|1660,0:1935|1661,0:859|1662,0:4163|1664,0:3122,3261,3412,3598,3746,3892,4196,4364|1666,0:343,353|1667,0:976|1670,0:1420|1671,0:1426|1672,0:1299,2158|1673,0:1250|1676,0:1022|1677,0:934|1678,0:835|1679,0:1774|1681,0:1755|1682,0:1020|1683,0:772|1684,0:793|1685,0:805|1686,0:1128|1687,0:832|1688,0:1745|1689,0:1180,1998,2632|1691,0:1810|1694,0:1178,1818|1695,0:1408|1696,0:1175|1698,0:1756|1700,0:1362|1701,0:1340|1704,0:1037|1705,0:1778|1706,0:890,1691|1707,0:1239|1708,0:897,1745|1709,0:812|1710,0:1071|1711,0:1122,1182|1712,0:779,3248|1713,0:2054|1714,0:1068|1715,0:2221|1716,0:1773,5784|1763,0:1865|1777,0:834|1778,0:936|1808,0:568,970|1815,0:3070|1820,0:745|1852,0:1108,1236|1860,0:5583|1861,0:940|1869,0:2061|1871,0:1103|1885,0:887|1890,0:1084|1892,0:312|1894,0:496|1895,0:1205|1897,0:504|1898,0:806|1899,0:1822|1900,0:388|1902,0:2218|1903,0:1992,2209|1907,0:1849|1911,0:1006|1913,0:1234|1914,0:744|1915,0:699|1919,0:694|1923,0:1985|1925,0:661|1926,0:990,1835|1928,0:682|1931,0:732|1932,0:1472|1937,0:753|1938,0:715|1939,0:621,1333|1940,0:601|1941,0:653|1942,0:703|1943,0:279|1944,0:1500|1945,0:734|1947,0:306|1948,0:1175|1949,0:810|1951,0:792|1953,0:746|1956,0:733|1957,0:706|1960,0:718|1964,0:3515|1965,0:1953|1966,0:356|1970,0:3223|1973,0:6411|1974,0:1220,4295|1983,0:1977|1986,0:2776,4844|1987,0:1673,3414|1988,0:1342|1989,0:1333,3539|1990,0:1357,3429|1992,0:3969|2181,0:1093|2192,0:1446|2204,0:2036,2229|2214,0:1664|2216,0:126|2451,0:1039|2452,0:1588|2455,0:3683|2457,0:315|2458,0:4242|2461,0:5375|2462,0:277|2463,0:8980,9119,9270,9456,9604,9750,10054,10222|2466,0:4298|2472,0:6232|2473,0:326,546|2478,0:928|2499,0:306|2502,131:0,11,385,430,453,570,716|2519,0:144|2520,0:127|2521,0:153|2522,0:358|2523,0:248|2524,0:61,751,973,1363|2540,0:159|2541,0:180|2542,0:640,2657,2814,3968|2544,0:593,1787,2942|2545,0:951,1871,4293|2546,0:455,1373,3691|2547,0:696|2548,0:727|2549,0:349,1249|2593,0:531|2628,0:361|2629,0:507|2630,0:792|2631,0:726|2632,0:1234|2633,0:1257,1369|2634,0:839,1064|2637,0:1131,1378|2638,0:459|2639,0:122|2641,0:1165|2644,0:3998,4175,4463,4634|2648,0:197,299|2651,0:773|2655,0:1527|2657,0:1668|2660,0:912|2667,0:3048|2675,0:246,371|2678,0:1819|2694,0:632,1118|2695,0:202|2696,0:918|2701,0:1325|2703,0:1177|2742,0:934,1043,1142|2744,0:1793|2777,0:1367|2792,0:485,1008|2794,0:3129,4624|2796,0:866|2800,0:2664,4514,5982,7882|2801,0:2324|2802,0:2406|2804,0:1260|2805,0:3648|2807,0:3828|2809,0:1258|2810,0:2886,3398|2812,0:2049|2813,0:2130|2815,0:2282|2816,0:2280|2819,0:2327|2820,0:1812|2893,0:1413|2928,0:954,1061|2941,0:114,1194|2942,0:103|2944,0:536|2954,0:124,1494|2960,0:4340|2988,0:486|3006,0:3057|3062,0:2481,2499|3192,0:1973|3194,0:1652|3197,0:1062|3201,0:4407|3203,0:12995|3208,0:643|3211,0:2198,4769|3218,0:6056|3220,0:1045|3225,0:1319|3231,0:1627|3232,0:1267|3233,0:3511|3235,0:1578|3236,0:1041|3241,0:1122|3269,0:348,695,884|3277,0:106|3281,0:1443|3302,0:1602|3305,0:145,1176|3306,0:146|3307,0:623|3309,0:5072|3317,0:4196,4454,4627|3327,0:2372|3332,0:1338|3427,0:8168|3439,0:2484,3934|3615,0:1040|3627,0:68225,68244|3728,0:1972|3767,0:655,714|3815,0:317|3816,0:313|3934,0:1035|3970,0:133,932|4239,0:430|4274,0:2721,2888|4292,0:1438|4294,0:230|4318,0:137|4319,0:556|4321,0:230|4322,0:620|4323,0:897|4330,0:892|4331,0:365|4332,0:388|4336,0:832,974|4340,0:651|4343,0:508,1167|4346,0:709|4351,0:1101|4364,0:1609|4453,0:832|4464,0:945|4466,0:765|4482,0:115|4499,0:3217|4577,0:541|4578,0:288|4579,0:269|4580,0:259|4581,0:247|4584,0:113|4585,0:1780|4590,0:423,1560,1674,2243|4594,0:1615,1958|4596,0:146|4598,0:470|4600,0:148|4602,0:517|4607,0:635|4610,0:2206,2898|4614,0:267,522|4615,0:170|4620,0:2789,4021,4767|4622,0:4785,4945|4624,0:1275|4628,0:3285|4634,0:2773,3008|4648,0:2037|4651,0:114|4706,0:761|4707,0:465|4708,0:377|4709,0:527,725|4742,0:777|4744,0:1127|4745,0:683|4748,0:800|4749,0:825|4750,0:2442|4781,0:98|4827,0:575|4829,0:558|4841,0:1420|4842,0:832|4843,0:1411|4849,0:258|4855,0:1322|4856,0:1823|4861,0:697|4862,0:688|4866,0:1270|4867,0:1170|4868,0:1553,2358|4871,0:1760|4879,0:4574|4881,0:3603|4898,0:1577,3971|4904,0:1123|4932,0:2166,3603,5872,6000|4938,0:338|4940,0:386|4942,0:587|4952,0:745,1754|4956,0:480|4960,0:1019|4961,0:1162|4962,0:1196|4963,0:1350|4980,0:724,1321|5006,0:530,613|5007,0:702,789|5008,0:597,684|5010,0:1152|5047,0:425|5050,0:690|5053,0:703|5055,0:474|5057,0:617|5059,0:530|5061,0:598|5063,0:582|5065,0:1035|5066,0:1207|5067,0:2485|5073,0:1192|5076,0:570,969|5077,0:1041|5083,0:3687|5084,0:1963,3752|5085,0:1041|5086,0:2007|5087,0:814|5089,0:781|5090,0:916|5091,0:2376|5093,0:959|5095,0:1554|5097,0:1696|5100,0:2111|5102,0:1129|5103,0:788|5117,0:1450,1632|5123,0:211|5126,0:215|5133,0:398|5134,0:634|5145,0:1059|5149,0:214|5151,0:254|5155,0:766|5187,0:810"/></pk>