<?xml version="1.0" encoding="UTF-8" standalone="no"?>
<pk><wd nm="correspondenc" rd="2695,0:340"/><wd nm="correspondence" rd="348,0:5009|353,0:6311"/><wd nm="cosign" rd="1239,0:2684,2747,2794,2803|3092,0:1041,1064,1104,1954,1977,2017,2439,2637|3162,0:64,633,718,1541,1592|3201,0:2562|3203,0:8178|3226,0:1413,1514,1657,1758,1857,1867,1908,1955,2015,3547,3622,4219|4410,0:151|4522,0:385,438|4568,0:846|4790,0:4532"/><wd nm="cosmetic" rd="4237,0:1096,1190,1974,2358|4261,2:50,110,174"/><wd nm="cost" rd="245,131:20,51,125,282,414,516,577,620,1033|265,0:433,1270|317,0:93|359,0:196|1383,0:161|1594,0:5534|1760,0:2191,2242,2278,2303,2363|1785,0:4298|1787,129:24,52,200|1796,0:346,383|1827,0:324|1830,0:153|1842,0:341|1856,0:7736,7798,7809|1860,0:2293,2436,2614,2685|1887,0:1217,1237,1252,1273,2627,2648,3954,3970|1888,0:1202,1222,1236,1257,2590,2611,3901,3917|1891,0:1691,1708,1887,1958|1906,0:2220,2253,2436,2507|1939,0:273,281|1954,0:304,312,341,411|1955,0:659,667,744|1959,0:943,951,1028|1964,0:2148,2194,4685,4731|1973,0:2782|1988,0:945|1989,0:2180,2206,2263|1990,0:2204,2230,2287|1992,0:1316,1343|2503,131:4,26,92,176,225,259,488,532,992|2527,0:2165,2219,2232,2287,2526,2538,2620,4468,4479|2542,0:2851,2864,2925,3043,3113|2544,0:1825,1838,1895,2014,2084|2549,0:2568,2595,2635,2652|2644,0:12554,12566,12594|3414,0:252,352,399,568|3606,131:15,34,78,150,288,663,729,760,848,1307,1629,2833|3627,0:2439,29799,29818|3648,0:1120,1143,1251,1360,1463,1580,1939,2102|3653,0:7432,7472,7584|3660,0:4969,5009,5101|3661,0:5243,5283,5371|3662,0:2634,2666,2751|3663,0:5487,5515,5630|3664,0:2665,2697,2782|3666,0:5173,5218,5275,6380,6393,6496|3671,0:518|3672,0:2117,3398,3438,3482|3673,0:2244,2323,4084,4124,4168|3674,0:1131,1152,1247,1342,1663,1694,1713,1741,2221,2574,2608,2637|3676,0:2301,2391,3616,3656,3700|3678,0:971,991,1063,1122,1161,1205,1409,2339,2426,3602,3642,3686|3724,0:1079,1094,1184,1418,1500,1516,1544,1568|3725,0:1376,1391,1481,1693,1747,1763,1793|3726,0:439,460,517,529,564,615,633,671,704,781,797,829,860,2059,2074,2094,2200,2263,2369,2389,2496,2559,4629,4658|3744,0:6297,6325,6421|3768,0:4356,4608,4626,6480,6520,6632|3792,0:1311,1330,1427|3809,0:2265|3874,0:2421,2452,4008|3878,0:98|3936,0:1616|3938,0:1616|3947,0:1618|3961,0:1613|3963,0:1619|4005,131:25,61,126,251,319,745,839,887,1330|4006,131:25,61,126,263,331,780,874,922,1365|4007,131:14,41,90,163,283,625,710,749,938,1173|4008,131:13,40,89,174,306,660,745,784,973,1207|4009,0:952|4025,131:17,53,111,192,463,557,605,1022|4218,0:636,655,690,715,767,873,931,979,1060,1136,1180|4263,0:4892,4923,5035,5088,5110,5142,5158,5173|4458,0:574|4655,0:997,1014|4661,0:2591,2608|4679,0:2390,2407|4836,0:1720|4995,131:13,30,76,180,241,564,622,734,831,952,1032,1145,1608|5011,0:2179|5035,0:1300,1323,1394,1419|5052,0:950,958|5056,0:506,514|5060,0:1481,1489,1536,1582|5061,0:1649,1665,1729,1752,1815|5066,0:2046,3135|5070,0:2504,2525|5074,0:2803,2816|5084,0:1170,1178|5090,0:1831,1846,1938,1974,2012|5095,0:426|5166,0:600"/><wd nm="cotton" rd="2862,0:346|2872,0:327|3204,0:257|4998,0:240"/><wd nm="cough" rd="1664,0:7838,8126|2463,0:14044,14332"/><wd nm="could" rd="119,0:409|199,0:742|203,0:644|207,0:207|208,0:662|212,0:200|213,0:603|222,0:686|232,0:691|237,0:721|490,0:4149|575,0:3444|1137,0:1732|1153,0:1694|1158,0:277|1212,0:1360|1224,0:1690|1235,0:1358|1346,0:322,10007,18343|1573,0:336|1582,0:14347|1792,0:500|1806,0:278|2046,0:382|2356,0:518|2360,0:120|2513,0:98,213|3205,0:2008|3222,0:2127|3231,0:1776|3270,0:965|3998,0:331|3999,0:360|4373,0:232|4628,0:1938,2362|5193,0:1692,1912|5199,0:1242"/><wd nm="counsel" rd="57,0:695|58,0:155|383,0:217,341|397,0:258,382|544,0:345|550,0:535|554,131:14,38,109,155,172,216,419,436,491,541,577,1138,1159,1276,1397,1424,1464,1517,1672|652,0:69,1885,2050,2072,2211|689,0:471,1596|3201,0:5769,5822,5885|3387,131:0,17,66,168,193,270,435,492,521,917|3401,0:228,334|3447,0:450,1147,1199|3448,0:2370,2981,3029,3046,3112,3161,3190,3237,3259,3423,3482|3627,0:5579,5619,5707,5834|3630,0:612|3687,0:57,79,102,167,247,292,310,516,624,832,871,903,942,1000,1164,1231,1546,1851,2043,2138,2550|3706,0:168,309|3707,0:212,374|3708,0:567,1037,1094,1158,1238,1434,1578,1703,1776,1824,1858,1878,1921,1960,2007,2093,2155,2232|3776,0:619|3909,0:216|3910,0:392,527|3911,0:40,175,483,1274,1298,1356,1427,1576,1700,1766,2074|3986,0:75,98,125,565,663,710,765,805,882,948,972,1061,1128,1469|4032,0:221,624,637,1311,1348,2319,2365,2415,2857,3343,3363,3513,4273,5786,5809,6079,6128,6151,6309,6687,6762,6855|4038,0:623,2262,3634,5198,5230,5275,5306,5327,5379,5483,5550|4072,131:9,34,287,335,692,722,758,805,843,888,1442,1472,1517,1556,1702,1864,1954,2138,2573|4073,131:5,27,130,184,499,535,556,603,631,665,1043|4496,0:494,569|4549,0:4122,4187|4640,0:10233,10285"/><wd nm="count" rd="254,0:545|382,0:202|399,0:3838|439,0:2887,2993,3058|443,0:1732,1756,1765,1873,1882|451,0:1658,1764,1829|452,0:4653,4759,4823|569,0:807|691,0:357|802,0:1548,1616|1044,0:919|1163,0:1244|1164,0:527|1185,0:3095|1190,0:1258|1191,0:541|1239,0:320,855,1044,1298,1570,1866,2177,2596,2841,3236,3410,3571,3733,3890,4249,4419,4727,5066,5377,5780,6257,6452,6644,6828|1263,0:233|1268,0:1183|1344,0:283,485|1361,0:211|1475,0:1242|1486,0:289|1488,0:326|1564,131:16,37,75,165,357,404,437,516,584,651,806,843,1058|1578,0:760,810|1619,128:27,457|1810,131:6,22,73,87,209,262,290,586,629,806|1811,131:6,28,86,122,182,216,344,462,677|1812,0:175|1813,2:85,241,847,907|1815,0:164,201,250|1817,131:5,20,58,133,204,267,500,561,659,719,749,802,829,942,1059,1287|1818,131:7,24,64,119,222,277,306,418,554,766|1860,0:58,352,877,1395,1928,2456,2945,3501,3583,3631,3648,3849,3996,4075,4115,4173,4200,4252,4334,5987|1863,0:58,146,280,298|1879,0:3209,3264,3325|1889,128:14,449|1890,0:73|1891,0:2049,2076,2135,2166|2000,0:229,389|2006,0:243|2063,0:1717|2084,0:314,1391,1501,1653,1957,1995,2035,2073,2112,2149|2090,0:377,450,475,646|2097,0:438,757|2161,0:3804,3826,3989,4011|2193,0:511,624,658|2214,0:3067|2224,0:450,769|2246,0:1622,1638|2248,0:1065,1101,1168,1229|2249,0:1103|2281,0:3192,3321|2314,1:52,120,520,1550|2338,0:192,785,909,1375,1488|2553,0:1073,1189,1748|2874,0:471|2888,131:4,21,85,132,165,235,415,448,467,496,736,804,884,1007|2889,0:170,225|2899,0:1066,1080|2905,0:6033,6136,7084,7123,7151,7198,7236,7528,7575,7643,7679|2922,0:2310,2342,2386,2411|2933,0:452,484,553,579|2937,0:368,630,651,672,695,795,848|2949,0:3685,3897|3003,129:10,25,69,2088,2212|3010,0:3410,3855|3012,129:4,17,31,69,486,514,620,662,678,737,873,1016,1087,1175,1303,1373,1460,1589,1660,1748,1876,1946,2033,2161,2230,2545,2677,2705,2826,2840,2947,3000,3035,3108,3136,3206,3238,3390,3451,3464,3476,3495,3555,3625,3639,3747,3767,3828,3898,3912,4020,4039,4099,4169,4183,4291,4310,4364,4439,4545,4582,4627,4904,4935,4994,5703,5821|3236,0:1148|3333,0:5042|3354,0:843|3627,0:23489,23503|3733,0:1738|3790,0:893|3839,0:2447|4094,0:3041,3173,3597|4146,0:2077,2209|4191,0:1660,1674,1768,1786,1896,1912|4200,0:1699,1713,1807,1825,1935,1951|4281,0:834,2007,2031,2204,2299|4558,0:986|4632,0:742|4716,0:719|4916,0:328,975,1008,1027|4974,0:2372|5039,0:537,590|5051,0:62,125,524,910|5078,131:6,22,73,87,202,267,317,345,523,857,920,985,1048,1225|5079,0:164,201,250,613,634,1109|5081,131:5,20,58,151,183,282,403,588,649,745,806,836,886,913,1028,1172,1426"/><wd nm="counter" rd="241,0:1045|1292,0:6100|1764,0:555|1765,0:1251|1766,0:698|1767,0:373|1768,0:435|1923,0:2678,2701|1932,0:2364,2387|1944,0:3085,3108|2248,0:310|3221,0:2533|3290,0:724|3348,0:131,302|3356,0:101|3361,131:21,55,219,276,367,506,901,997,1035,1172,1489|3372,0:1116|3385,131:4,16,60,181,197,293,435,565,716,760,883,1052,1082,1214,1339,1359,1422,1446,1837|3386,131:4,33,97,137,239,331,344,427,451,551,592,667,708,937,1004,1229,1244,1284,1319,1410,1528,1871,2113,2163,2254,2281,2296,2323,2371,2762,3015,3164,3490|3393,0:304,448,676|3452,0:593|3456,0:423|3479,0:131|3496,0:190,267,603,676,734|3497,0:628,675,733|3498,129:17,44,171,204,297,536,575,1391,1447,1498,2554|3502,0:285,611,713,762,869|3534,0:2450|3535,0:1621|3547,0:2725,2902,2988,3121,3212,3287,3348|3548,0:1735,1913,2000,2134,2226,2301,2362|3567,0:3251|3568,0:325,400,734|3571,0:527,659,830,865,960,1038,1112,1159,1543,1557,1608,1660,1708,2478,2577,3512,3611|3572,0:254,361,432,548,998|3575,0:378,2347,3391,3498,3562|3594,0:286|3603,0:188,410,575,621,843,1101,1373,1477,1578,1703,1859,2190,2218,2324,2371|3607,0:817|3611,0:776|3613,0:785|3627,0:10684,10749,10818,10928,10995,11067,11117,11166,11232,11275,11307,11348,11604,11722,11804,11898,12133,12235,12304,12379,12472,12560,12693,12751,12951,21822,21901,21938,22569,22819,22878,22968,34720,34735,43357,43463,43567,43671,43779,43882,43985,44092,44195,64912,65018,65121,65225,65333,65437,65540,65646,65749|3636,0:383,560,1827,2084,2254,2358,3641,4384|3641,1:52,73,122,221,269,388,432,480,622,741,851,981,1100,1210,1351,1463,1828,3590,3864,5641,5727,5814|3642,0:327,1236,1286|3686,0:57,73,631,669,765,971,1134,1357,1385,1752,1955,2009,2071,2651,2755,2843,2947,3026,3113,3201,3290,3428,3512,3536,3969,4117,4362,4509,4754|3699,0:487,527,571,678,7917,7971,8788,8842|3757,0:797|3761,0:929|3766,0:2749,2812,2870,3020,3032,3091,3151|3786,0:138,180|3787,0:246|3827,0:7362,7408,7426,7445|3839,0:79,95,115,216,652,945,1140,1448,1627,2222,2245,2272,2544|3853,0:975,990,4374,4389|3866,0:69,96,120,580,674,750|3874,0:7511,7531,7553,7567,7586|3892,0:85,104,208,292,527,595,720,848,936,1021,1155|3893,0:537,577,616|3894,0:543,583,622|3921,0:95,323,419,511,590,739,897,1062,1562,1732|3923,0:2147,2171,2192|3924,0:6366,6383|3925,0:6438,6455,6516,6779,6796|3926,0:1150,1174,1195|3927,0:301,316|3928,0:356,4999,5014,6759|3929,0:1495|3939,0:8791|3941,0:6552|3942,0:5686|3950,0:1027,1051,1072|3952,0:1589|3965,0:8136|3980,0:3228|4001,131:4,26,77,156,197,210,254,330,385,441,461,530,564,956|4014,0:178,287,337,869,937,997,1112|4015,0:1486,1998,2042|4016,131:6,31,99,135,159,226,263,306,369,468,506,573,639,676,749,766,789,838,890,1109,1180,1194,1234,1324,1356,1495,1661|4029,0:2368|4030,0:2254|4031,0:479|4032,0:442|4033,0:389|4037,0:491|4041,0:1882|4044,0:1486|4047,0:112,174,237,280,384,452,471,553,618,929,984,1161,1534,1576,1624,2170,2192,2307,2389,3442,3468,3516,3531,3602,3644,3692,4130,4152,4190,4205,4337,4397,5500,5542,5590,6137,6577,6599,6660,6742,7715|4048,0:307,532,833|4049,0:813,1284|4050,0:103,176,290,361,530,579,643,1382,1439,1531,1640,1675,1725,2302,2590,2641,2677,2757,3130,4074,4113,4355,4455,4492,4562,4806,4953|4051,0:123,186,292,351,503,552,618,736,1462,1519,1605,1695,1804,1839,1889,2918,3207,3227,3244,3280,3360,3733,4657,4696,4941,5041,5078,5148,5262,5477|4052,0:170,228,356,876,916,1379,1615,1801|4053,0:148,313,579,727|4054,0:139,404,567,936,1006,1667,1812|4055,0:131,388,551,1003,1073,1740,1885|4069,0:111|4077,0:544|4078,0:403|4079,0:574|4080,0:361,2151|4082,0:630|4084,0:704|4087,0:337|4088,0:313|4089,0:346|4090,0:494,2398|4091,0:429,1583|4092,131:4,20,77,138,174,225,389,486,525,554,655,694,768,841,889,966,995,1048,1076,1142,1156,1195,1358,1662,1753,1809,1886,1901,1942,2136,2303|4093,131:4,21,81,167,179,232,286,366,445,498,565,618,647,729,746,787,937,1015,1086,1184,1257,1301,1365,1547|4094,131:4,31,101,197,262,322,376,409,683,759,881,1216,1291,1508,1634,1834,1887,1926,2003,2017,2122,2378,3481,3508,3694,3893|4095,0:3275,3290|4096,0:5622|4097,0:384,463|4098,0:1626|4099,0:414|4100,0:503|4101,0:1838|4115,0:560|4117,0:674|4118,0:684,3413|4119,0:2379|4120,0:2246|4127,0:1446|4128,0:333|4129,0:714|4130,0:575|4131,0:357|4133,0:377|4134,0:365|4135,0:457|4136,0:414|4137,0:572|4138,0:638|4139,0:855|4141,0:474|4142,0:417|4143,0:4661|4144,131:4,20,69,126,162,214,367,464,498,527,628,668,742,815,863,940,973,1026,1054,1120,1134,1173,1336,1640,1732,1788,1865,1880,1921,2115,2282|4145,131:4,21,82,161,173,231,290,386,465,518,585,638,667,749,766,807,957,1036,1107,1206,1279,1323,1387,1569|4146,131:4,31,104,196,260,320,374,407,709,1044,1119,1336,1462,1640,1709,1748,1836,1919,2527,2581,2778|4147,0:368,447,1686|4149,0:519|4150,0:427|4159,0:773|4160,0:597|4161,0:706,3486|4169,0:671|4173,0:557|4183,0:359|4184,0:170,228,356,916,956,1050,1482,1718,1904|4188,0:683|4189,0:606|4190,131:4,20,94,168,204,274,398,538,635,686,736,764,830,844,883,1065,1384,1456,1536,1577,1699,1773,1929|4191,131:4,25,109,205,280,340,394,427,684,764,860,986,1056,1106,1143,1197,1222,1249,1317,1479,1573,1633,1720,1880,2068,2178,2271,2358,2943,3039,3213,3228,3375,3487,3807,3881,3908,3947,4048,4127,4269|4192,0:1202,1276|4196,0:707|4197,0:586|4199,131:4,20,114,188,224,306,449,602,699,755,808,836,902,916,955,1137,1456,1528,1608,1649,1771,1845,2001|4200,131:4,25,121,217,304,364,418,451,708,788,884,1010,1092,1145,1182,1236,1261,1288,1356,1518,1612,1672,1759,1919,2107,2217,2310,2397,2982,3078,3252,3267,3414,3526,3846,3920,3947,3986,4087,4166,4308|4205,0:616,1439|4210,0:1241|4230,0:2689,2710|4286,0:284|4291,131:4,25,96,114,174,248,396,442,478,543,613,649,715,827,954,1049,1333|4478,0:3139,3436|4479,0:11221,11518|4605,0:453|4610,0:1140,1209|4634,0:6812|4640,0:2929"/></pk>