<?xml version="1.0" encoding="UTF-8" standalone="no"?>
<pk><wd nm="operational" rd="387,0:291|395,0:81,135,239|468,0:3933,4082|1238,0:1586|1345,0:1524|1471,0:2487|1879,0:667|2500,0:1277|2509,0:201|2542,0:237,2304|2544,0:237,1477|2601,0:8739|2915,0:554|2919,0:813|3120,0:664|3122,0:1029|3196,0:2150|3342,0:3928,4019|4790,0:88,151,267,4514|4822,0:467,529,742|4823,0:1467|4826,0:463|5158,0:255,299|5162,0:96|5163,0:280,324|5164,0:80|5192,131:0,17,63,150,204,510,572,601,681,943"/><wd nm="operations/procedure" rd="2870,128:1282"/><wd nm="operativ" rd="2753,0:1729|2838,0:221|2840,0:223|2860,0:190,205|2873,0:159,176|2877,0:241|2878,0:311|2879,0:374|2880,0:299|2883,3:4,26,81,134,278,333,367,696,787|2891,0:1676|2904,0:512,554|2908,0:234,328|2912,0:655,756,838,854,903,950|2922,0:2057,2089,2178,2211|2933,0:952,996,1375,1420|2941,0:1886,1924|2950,0:1267|2952,0:2068|2961,0:1099,1127,1154|2965,0:2245,2283,2337,2365,2416,3203|2969,0:392,430,936|2971,0:53,973,1019|2974,0:785,1307|2990,0:398,920|2991,0:519,700|2992,0:1099,1127,1154|2993,0:425,460,597|2994,0:173,213,266|2995,0:999,1073,1124|2996,0:441,469|2997,0:416,451,642|2998,0:311,346,762|3000,0:172,220,408|3001,0:304,339,543|3006,0:406,441,492,532,646,670,1062|3009,0:474,502,550|3013,0:495,530,667|3014,0:255,390|3015,0:500|3016,0:66,81,97,291,426"/><wd nm="operator" rd="67,0:556|88,0:2048|92,0:1388|102,0:364|272,131:11,37,97,143,179,240,271,341,373,430,453,494,532,787,860,954,1016,1177,1360,1603,1683,1785,1962|276,131:0,15,61,203,221,361,563,600,635,683,735,809,848,871,901,928,1080,1132,1165,1250,1337,1514|277,131:0,26,111,168,197,343,533,567,626,678,701,731,769,967,1077,1097,1180,1314,1405,1619|315,131:7,29,96,175,233,280,335,358,395,429,593,693,903|339,0:82,314,338,409,591,688,813|343,0:57,296,364,400,418,545,676,761,790|344,0:78,200,224,348,523,639|345,0:212,290,358,634,702,789,857,946,1018,1171,1251,1486,1814,1885,2032,2112,2287,2399,2589,2633,2792,2895,3030,3113,3225,3306,3411,3481,3707,3825,3970,4059,4232,4312,4402,4517,4595,4702,4790,4899,4988,5095,5164,5258,5338,5433,5514,5610,5694,5803,5867,5953,6019,6111,6175,6332,6412,6480,6570,6636,6723,6788,6878,6956,7056,7129,7289,7362,7429,7501,7570,7663,7737,7842,7919,8520,8545|347,0:219,300,544,643,721,889,955,1118,1190,1430,1494,1649,1715,1809,1873,1961,2048,2161,2251,2359,2449,2619,2744,2981,3060,3277,3359,3428,3582,3651,3828,3898,4070,4173,4351,4450,4531,4617,4694,4773,4852,4932,5015,5075,5157,5231,5368|378,0:74,523,548,616,647,814,1011|406,0:634|409,0:644|415,0:2014|418,0:588|419,0:788|422,0:633|443,0:4404,4458,4522|659,0:1154,1180|765,0:4131|813,0:799,1092|1065,0:1358,1393,1440,1514,1671,1739,1799,1836,1887,1938,1998,2068,2108,2160,2221,2292,2327,2388,2599|1076,0:1780,1795,2739,2754,3481,3496,4229,4244,5229,5244|1418,0:1063|1437,0:942|1636,0:655,1926,1943|1639,0:229|1640,0:194|1642,0:193|1644,0:9321,9395,10035|1653,0:920|1666,0:978|1669,0:884|1670,0:2440|1671,0:517,616|1673,0:719|1674,0:798|1677,0:837|1678,0:736|1679,0:355|1682,0:169,371,487|1684,0:697|1685,0:707|1688,0:266,1040,1630|1690,0:4010|1691,0:395|1692,0:534,1148,1384|1694,0:1072|1695,0:1311|1696,0:739|1698,0:1659|1700,0:512|1701,0:1235|1705,0:1680|1707,0:214,369|1710,0:446|1711,0:796,1808|1713,0:510,1106,1921|1714,0:286|1715,0:678,4233,4986|2050,0:1201,1226,1449,1474|2451,0:1252|2622,0:2110|2646,0:1832|2739,0:260,278,349|3168,0:2176|3253,0:800|3257,0:881|3283,0:617|3289,0:614|3291,0:1179|3309,0:3306,3405|3311,0:293|3313,0:779|3314,0:253|3318,0:323|3320,0:288|3322,0:336|3325,0:2049|3329,0:1168|3330,0:337|3333,0:666,1222,1668,2481|3334,0:1258|3337,0:1154|3338,0:2347,2446|3458,0:1251,1338|3459,0:1228,1315|3466,0:930,994|3467,0:928,992|3470,0:837,901|3471,0:846,910|3479,131:21,50,149,182,332,408,449,1286|3496,0:208,288,741|3497,0:290,740|3498,0:1528,1566,1612|3502,0:245|3509,0:399|3627,0:8911,9938|3786,0:81,122|3839,0:1725|4594,0:332,375|5129,0:498,525"/><wd nm="operator’" rd="3497,0:827"/><wd nm="ophthalmology" rd="2867,0:296,362"/><wd nm="opiat" rd="1161,0:3958,3984|1188,0:4297,4321"/><wd nm="opinion" rd="1137,0:3392,6037|1153,0:3374,4898|1212,0:3040,4564|1224,0:3371,5189|1235,0:3038,4562"/><wd nm="oppos" rd="1292,0:4522"/><wd nm="opt" rd="484,0:226|2337,0:1938|3278,0:7783|3281,0:6841|3282,0:7631|4956,0:1468,3117,3226,3295"/><wd nm="optimal" rd="3107,0:475|4956,0:1331,1482,1529,1776,1862,1954|4974,0:598|4978,0:1443,1456,1469"/><wd nm="optimization" rd="1791,0:399"/><wd nm="optimum" rd="1805,0:215"/><wd nm="option" rd="9,0:553,618,685,1934|10,0:226,291|11,0:352|12,0:138|24,0:212|25,0:189|38,0:2952,2998,3347,3458,7136,7825,8221,8280,10708|45,0:714|69,0:406,523,818|75,0:841,1135|76,0:671|79,0:996|83,0:136,257|86,0:2141|87,0:397|100,0:1181,6215|101,0:971|102,0:540|107,0:272,1282|117,0:311|125,0:672,769|126,0:777|129,0:749|130,0:791,834,1010|132,0:740,778,833,1099,1308|133,0:563|135,0:505,940,994|136,0:643,1034,1088|150,0:1421,1430,2582,2846|163,0:660,742,921|164,0:1403|168,0:95|187,0:460,490,636,679,1000,1098,1136,1445,1475,1618,1661|193,0:106|197,0:439,679|199,0:844|203,0:745|206,0:405,630|208,0:764|211,0:544|213,0:704|222,0:787|224,0:219|225,0:1342,1351,1384|231,0:331|232,0:792|237,0:822|259,0:363|267,0:109|313,0:225|333,0:825|362,0:238|392,0:460|402,0:663|404,0:427|415,0:300,665,1089,4242|423,0:553,618,650,819,883,1460|424,0:180|431,0:5829|434,0:75|435,0:335|443,0:7730|456,0:354,537,717|469,0:2062|473,0:1002|483,0:299|484,0:235,381|494,0:195|505,0:394|517,0:289|547,0:640|556,0:301|571,0:1005|577,0:477,509|664,0:199,1206|681,0:2312|692,0:1297,1382|697,0:7334,7405,7660,7731|707,0:314|717,0:377|724,0:278|747,0:542,598|748,0:447,522|754,0:765,844,859|755,0:622,705|802,0:156|807,0:6426|841,0:482,523,564|862,0:1475,1578|863,0:1354,1457|864,0:875,979|866,0:1323,1427|867,0:1262,1365|868,0:1170,1273|872,0:376|877,0:1528,1569|882,0:904,1008|919,0:78|946,0:599,982,998,1034,1044,1083,1118,1166,1242,1278,1316,1406,1423,1481,2178|954,131:10,26,297,341,369,485,637|958,0:500,734,800|1044,0:1389,1436,3078,3123,3543,4061,4156,4228|1045,0:233,410|1050,0:530,603,778,1872,1924,1967,2070,2100,2154|1053,0:1283,1415,1454,1631,1658|1055,0:1649,1806,1886,2014,2150|1058,0:150,245|1065,0:1550,1589,2576|1068,0:1861,1895,1970,2076,2195,2482,2516,2591,2697,2816|1071,0:1651|1076,0:914,1290,1992,2262,2951,3693,4441,4770,5441,6238|1086,0:1683,4405,4476,4597,4637,4693,4812,4849|1087,0:233,1398,1912,2848|1097,0:639,660|1099,0:471,718,1171,1629|1113,0:857|1123,0:257,2342,2441|1128,0:193,386,446,859,932,993,1469,1539|1133,0:404|1135,0:762,3380|1137,0:6934|1148,0:407|1150,0:765|1161,0:2411,4010|1165,0:3119,3151,3326|1168,0:65,6248|1173,0:64,6107|1183,0:58,6077|1188,0:2425,2536,3871,3906,6902,6937,7218,10997,11028,11320,12957|1201,0:72,6143|1207,0:408|1209,0:766|1213,0:2979,3173,3355,3570,3787,3981,4165,4358,4541,4788,4985|1219,0:405|1221,0:763|1225,0:857|1230,0:407|1231,0:765|1238,0:602,1023,1059,3844,3979|1245,0:559|1246,0:380,399,458,3960|1254,0:1004|1264,0:2010,2048|1267,0:1034|1289,0:816,990,2183,2358|1290,0:1029,1047,1130|1295,0:4073|1298,0:3173,3222|1301,0:4557|1304,0:242|1308,0:3223|1310,0:1215,1258|1318,0:163|1345,0:540,961,997,4615,4750|1346,0:2808,2841,4738,5110,6147,8044,8416,9448,10036,10527,11142,11174,13071,13443,14481,16378,16750,17783,18372,18864,19999,21202|1389,0:280,403,522,651|1410,0:520,602|1427,0:88|1428,0:95,1319|1429,0:1661,2482|1430,0:101,1278|1431,0:71,1376|1435,0:614|1436,0:445,2737|1458,0:577|1459,0:265|1461,0:1023|1471,0:1637,1843,1966,2084,2203|1474,0:3545,3697,3761,5108|1479,0:254|1491,0:532,557|1497,0:718|1499,0:858|1502,0:797|1504,0:1019|1505,0:1048,1243,2369,2791|1506,0:1020,1217,2367,2796|1511,0:816,933,1031,1147|1516,0:1524,2206|1518,0:451,572,674,794|1526,0:1313,1875,2700,2948|1564,0:145|1565,0:300|1575,0:280|1580,0:873,1201|1582,0:1163,2511,5603,6594,6718,6901,7879,7991,8158,11395,11558,11711|1592,0:345|1594,0:2536,2984|1597,0:1214,1498,1791|1600,0:676|1607,0:447|1608,0:677|1611,0:932,950|1633,0:524|1637,0:515,603,677,918,3948|1638,0:139,231|1642,0:2544,3021|1645,0:186|1660,0:1844|1663,0:3650|1669,0:10561,10803|1679,0:2583|1691,0:2631|1692,0:145|1705,0:5335|1711,0:961|1712,0:1744|1716,0:1952|1719,0:313|1720,0:331|1727,0:655,913|1731,0:399|1733,0:315|1745,0:796,811,858|1771,0:265|1775,0:698,727,789,872,939|1777,0:793|1778,0:895|1780,0:635|1781,0:568|1782,0:590|1783,0:475|1786,0:534|1788,0:554|1789,0:484|1790,0:505|1791,0:2117|1808,0:582|1811,0:404|1812,0:582|1815,0:1728,3375|1817,0:1016|1818,0:509|1819,0:528|1828,0:830,910,989|1835,0:470|1837,0:431|1838,0:657|1839,0:564|1840,0:758|1841,0:478|1842,0:657|1843,0:506|1844,0:627|1845,0:594|1846,0:564|1847,0:487|1848,0:685|1849,0:795|1850,0:552|1851,0:542|1852,0:470|1857,0:8532,8634,9901|1860,0:5268,5362|1866,0:514,640|1868,0:1367,1397|1870,0:1811|1891,0:2579|1893,0:307,337|1899,0:1911,1941|1902,0:132,162|1905,0:2094,2124,2361|1909,0:117,126|1912,0:237,277|1916,0:1432,1563,1713,1850,2117,2263|1939,0:755|1968,0:1303|1972,0:649|1974,0:1923|1975,0:1005,1024,1090|1981,0:1319,1359|1984,0:557|1985,0:716|1987,0:1142|2016,0:719|2017,0:1401|2040,0:273|2067,0:576|2073,0:774|2074,0:762,818|2075,0:574,692|2077,0:604|2079,0:632|2080,0:440,496|2084,0:1746|2151,0:1120|2161,0:4598|2169,0:1148|2173,0:239,255|2184,0:872|2186,0:1066,1126|2187,0:207|2188,0:296|2197,0:316|2200,0:607|2201,0:328,428|2205,0:115,150|2207,0:547|2211,0:394|2217,0:1147,1293|2227,0:1150,1166|2229,0:1498,1514|2230,0:4369|2235,0:891|2244,0:999,1022|2247,0:472|2271,0:967|2272,0:539|2275,0:266|2279,0:248|2280,0:888,1143|2288,0:243,626|2331,0:550|2332,0:371|2338,0:455|2350,0:256|2405,0:6545,6571,6631,6711,6755,6887,6990,7115,17971,18031,29973|2409,0:199,286,375,468,562,657,821,923|2423,0:510,590|2426,0:730|2438,0:611|2446,0:109|2455,0:3270,3283,3566|2458,0:1125|2461,0:7579|2463,0:449,5108|2472,0:8867|2473,0:778,901,1542,1608|2483,0:94,489,1053,1579,1659,1716|2496,0:2644|2497,0:3023|2522,0:604|2523,0:492|2524,0:1103,1489,1784,2096|2527,0:2932,5802|2537,0:360|2538,0:83,405,437,733,759|2539,0:377|2542,0:546|2544,0:498|2613,0:332|2616,0:374|2644,0:660,6299,6337,6387,14455|2673,0:4579,4626,4810,4854,5223,7028|2705,0:387|2709,0:697,1487|2712,0:809|2720,0:654|2752,0:182|2753,0:215|2800,0:8282,8330,8420|2804,0:344|2806,0:52,250,483,534,886,937|2807,0:2821|2808,0:485,707,775|2809,0:389|2810,0:205,354,422,708,874,4092,9226|2811,0:180|2891,0:916,938|2893,0:1665|2894,0:957|2910,0:470,489,572,631,685|2911,0:953|2916,0:838|2917,0:749|2941,0:1417|2943,0:1006,1042,1077|2944,0:1280,1290,1451,1504|2946,0:1395,1486,1568,2180,4420|2950,0:207,1403|2952,0:1925,1949,1980,2366|2953,0:1089,1113,1144|2954,0:1717|2955,0:1081|2956,0:753|2966,0:218|2967,0:372,443|2970,0:109|2973,0:979,1001|2976,0:442,513|2977,0:454,525|2978,0:341,412|2982,0:528|2983,0:5716,5733|2989,0:190,990|3002,0:636,1271,1304,1397|3010,0:969,3078|3027,0:801|3032,0:435|3034,0:1777|3043,0:1627,1743|3044,0:1074,1183|3048,0:955|3052,0:1545|3055,0:3545,3607|3064,0:2032,3226,7445,7561|3068,0:7302,7357,7596,10693,10755,13460,14301|3070,0:433|3071,0:827,3613,4464|3073,0:1507,6471,6929,7001|3075,0:869,970,1158|3083,0:1008|3092,0:560,592,1363,1377|3093,0:593,626,732,746|3114,0:596,1310|3134,0:277|3141,0:2385,2412,5321,6294,7305,7393|3142,0:4014,4677|3143,0:1150,1443,1472,1588,2027,2128,2528,2827,3775|3149,0:680,759|3153,0:507|3161,0:1903,1926,1964,2107|3168,0:3599,3621|3192,0:393,408,428,625,724,843,944,1032,2157|3193,0:1001|3196,0:600,1874,2674,3021,3232,4253|3202,0:105|3203,0:456,647,785,849,957,1348,1675,1728,1784,8285,8338,8394,12244,12575,12624,12715,13899,13980|3204,0:58|3205,0:7002,7055,7111|3206,0:665|3209,0:1064,3076|3210,0:424,592,771,1159|3213,0:407,2850,6798|3214,0:811,892|3215,0:232,453|3218,0:54,1102,1183,4964,5323,5654,5703,5794,14022,14053|3221,0:1984,2001|3222,0:126,385,1625,1958,2031,3884,3953,4053,4264,5500,6235,6306,6539|3225,0:3777,3838,3957,6755,7965|3231,0:2341|3233,0:7349,8981|3234,0:185|3236,0:1225,2184|3239,0:568,597|3271,0:1652,5585,5659,5778,5896,6070,6348,7266,11197,11825|3292,0:32,134,829,899|3293,0:65,274,1074,1124|3294,0:305|3295,0:47,193,258,342|3296,0:71,218|3297,0:238|3298,0:204,316|3299,0:364|3300,0:735|3330,0:513|3333,0:2248,3809,3903,3954,4012,4217|3334,0:1012,5380|3335,0:1315,1393|3337,0:908|3338,0:901|3347,0:1795|3353,0:366|3356,0:466|3367,0:204|3381,0:518|3385,0:1169|3388,0:327|3389,0:369|3408,0:666|3414,0:224|3419,0:1172|3427,0:563,3953|3432,0:406|3433,0:511|3440,0:661|3441,0:448|3442,0:2627|3443,0:1911|3447,0:551|3449,0:534|3453,0:517|3460,0:243|3463,0:296|3464,0:370|3465,0:643,809|3468,0:183,1393|3469,0:435,1502|3475,0:936,992|3476,0:1022,1078|3477,0:1066,1122|3478,0:907,963|3479,0:585,641|3481,0:1030,1086|3484,0:974,1030|3485,0:912,923,1014,1070|3488,0:483,627,1319,2053,2143|3489,0:916,927,1018,1074|3493,0:7386,7466,7584,8094,8151,8212,8309,8367|3510,0:815|3512,0:284,368,796,983|3515,0:692|3528,0:462|3529,0:431|3534,0:596,2047|3537,0:272|3545,0:294|3555,0:337|3560,0:1513,1530|3562,0:338|3564,0:452|3565,0:462|3578,0:247|3585,0:1346|3586,0:972|3587,0:1504|3599,0:627|3603,0:208,528,1213,1293|3605,0:402|3607,0:554,635,2838,3140|3608,0:250|3609,0:219|3610,0:246|3611,0:513,594,3266,3570|3613,0:522,603,3926,4228|3615,0:585|3616,0:555|3617,0:473|3618,0:477|3621,0:317|3627,0:13064,13966,16460,16847,24246,24578,29958,29987,33915,37185,37217,37252,63609,63652,63730,63790,63873,63922,64197,64264,64433|3632,0:77,455|3641,0:149|3642,0:229|3646,0:965|3653,0:6705|3660,0:207,2766|3661,0:183,2963|3663,0:4672|3665,0:379,883,902,1190|3666,0:1182,4447,5231|3668,0:992,1004,1097,1979|3669,0:1239,1251,1341,2254|3672,0:2516|3673,0:3294|3676,0:2745|3678,0:2787|3679,0:1232|3680,0:4812|3689,0:962|3718,0:3317|3719,0:1877|3733,0:213|3736,0:859,899|3744,0:5655|3756,0:187,701,792,1231,1253,1745|3757,0:208,2171,3162,3661,4182,4699,5350,6295,6784,7285,7802|3758,0:1628,2121,2616|3761,0:319,2136,2642,3150,3727,4233,4741,5326,5832,6340,6919,7425,7933,8809,9328,9849,10448,10967,11488,12096,12615,13136,13736,14249,14764|3773,0:791,831,1560|3779,0:317|3783,0:826|3784,0:487|3786,0:377,393|3787,0:938|3790,0:2323|3812,0:577,594|3815,0:2883|3823,0:7509|3824,0:386|3827,0:1413,1434|3831,0:1524,1545|3835,0:684,699|3840,0:77,453|3850,0:1611|3852,0:1652|3853,0:405,426,6932|3856,0:1253,1407,2622,2668,2822|3857,0:1330,1484|3874,0:1105,1126|3880,0:233|3883,0:261|3891,0:425,435|3896,0:1258,1273,2073|3903,0:518|3911,0:401|3913,0:1096,1115|3914,0:1103,1122|3916,0:75,97,1685,1707|3917,0:988,1007,1083|3918,0:1047,1066,1142|3919,0:1105,1124|3922,0:2126|3923,0:525,553,1856,3056,7367|3924,0:2397|3925,0:2675|3926,0:859,1665|3928,0:251,318,381,543,2142,6606|3929,0:596,620,696|3931,0:274|3933,0:230|3935,0:251|3937,0:278|3943,0:227|3945,0:260|3946,0:263|3948,0:88,1204|3950,0:575,596,754,1452,8641|3952,0:688,712,788|3954,0:271|3956,0:288|3958,0:288|3960,0:273|3962,0:290|3966,0:704,719|3972,0:737|3975,0:712,727|3982,128:12,3788|3987,128:4,27,3358|3988,128:4,30,3279|3990,0:498|3991,0:552|3993,0:222|3994,0:381|4001,0:337|4012,0:438|4018,0:414|4019,0:579|4020,0:1079|4022,0:1414,1431|4023,0:475,1095|4032,0:711,3033|4034,0:409|4035,0:265|4037,0:2879|4038,0:451,2199|4042,0:312,791|4043,0:724|4047,0:400|4048,0:1902|4050,0:490,604|4051,0:463,579|4052,0:1578|4053,0:912|4054,0:302|4057,0:369|4060,0:411|4062,0:432|4064,0:274|4066,0:314|4067,0:270|4071,0:948|4072,0:525|4077,0:344|4078,0:510|4081,0:435|4082,0:392|4083,0:521|4084,0:416|4090,0:427|4091,0:362|4096,0:4767|4099,0:346,1689,2064|4100,0:436|4105,0:1188|4106,0:573,1260|4107,0:767,1285|4113,0:1619|4114,0:1820|4121,0:1327|4122,0:803,1351|4123,0:822,1473|4125,0:1936|4126,0:2031|4129,0:281,600|4131,0:251|4138,0:304|4140,0:348|4141,0:407,657|4142,0:350|4143,0:3723|4145,0:190|4148,0:284|4149,0:452,1368,1743|4150,0:360|4152,0:1389|4153,0:334,1160|4154,0:660,1237|4157,0:1466|4158,0:1819|4165,0:429|4167,0:601|4168,0:639|4174,0:593|4178,0:380,975|4184,0:1681|4193,0:3658|4202,0:75|4205,0:259|4236,0:676,692,728|4247,0:666,682,718|4267,0:603,861|4274,0:654,1168,1466,5916|4283,0:1695|4291,0:982|4313,0:2595|4318,0:74|4330,0:963,1057|4377,0:196|4406,0:318|4415,0:727|4430,0:737|4433,0:677|4459,0:474,859,903,956|4475,0:330|4479,0:3104|4480,0:4368,4569,4782|4492,0:3131,3991,4243,5196,5319|4499,0:2825,2881,3285,3558,3834,3982|4503,0:666|4505,0:688|4507,0:661|4509,0:706|4511,0:699|4519,0:459|4527,0:300,393|4538,0:93|4549,0:1938|4557,0:860,931|4560,0:208,263,320,379,506|4567,0:600,644|4572,0:1423|4575,0:159,214,271,325|4591,0:1809|4592,0:1548|4593,0:391,1354,1912,1966,2786|4594,0:107,116,175|4611,0:5220|4612,0:370,452|4619,0:455,580,709,826|4620,0:5570|4622,0:2965,5078,10014|4637,0:1650|4640,0:5031,5112|4642,0:756|4643,0:265,682,821|4680,0:2592|4689,0:2777|4697,0:394|4700,0:669|4711,0:141,464,482,588,728,799|4721,0:2012|4724,0:2055|4734,0:2373,2523,2532|4742,0:603|4745,0:1024,1058|4747,0:474|4748,0:391|4749,0:731,961|4750,0:788|4772,0:568|4788,0:320|4790,0:178,237,3455,6830|4792,0:468,523|4795,0:318|4810,0:1818,2006|4811,0:918,989|4813,0:2706|4821,0:758|4830,0:391|4831,0:1276,1518|4832,0:1399|4834,0:721,1357,1393,1401|4835,0:897|4837,0:935|4838,0:1456,1550|4841,0:697|4843,0:864|4845,0:392,666,695|4850,0:1140|4853,0:1088|4854,0:346|4855,0:352,475|4859,0:216|4861,0:941|4862,0:1160|4863,0:993,1688,1724,1732|4865,0:626,673,1129|4866,0:503|4869,0:1713,1774,3628,3665|4871,0:1432,2358,2533|4873,0:1960|4874,0:48,98|4878,0:2079|4879,0:3756,3776,5199,6426,6604,6785,6837,6923,7200,8804,8853,9026,9075,9596,10751|4881,0:245,1991,3197,4206,4247,4352,4437,4615,4796,4875,4923,5001|4882,0:921|4885,0:639,1384,1421|4886,0:881,889,3081,3335,3364|4887,0:1322|4888,0:4409,4429|4889,0:853,1627,1714,1734|4892,0:741|4893,0:3344|4894,0:624,1391,1515,1841|4898,0:808,3131|4904,0:609,664|4910,0:249|4912,0:282,369,458|4913,0:349,414,505|4915,0:616,772,936|4955,0:1091,1106|4957,0:1333|4960,0:623,639,669,771,894|4973,0:1803|4975,0:263|4977,0:2552,3665|4980,0:235|4982,0:824|4984,0:1206|5004,0:1152,1188|5043,0:668,770|5050,0:2680,2689,2778|5052,0:835,857,1011,1135|5056,0:567|5064,0:1431,1585,1687|5071,0:4588|5073,0:2691,2700,2789|5074,0:2772,2795|5076,0:584|5077,0:1000|5081,0:1128|5082,0:635|5104,0:50,333,364|5105,0:41,321,354|5106,0:63,305|5107,0:53,147,276,508|5108,0:21,283|5109,129:4,15,98,467|5111,130:12,79,214,381,400,511,780|5112,0:37,295,326|5119,0:393,449,586,717,804,853,1038,1057,1108,1246,1310|5141,0:525,624|5165,0:4352,5157|5178,0:514,1061,1080,1138,1160,1179,1212,1421,1487,1559,1608,1754,2039,2093,2165,2214,2299,2468,2613,2752,2809,2881,2930,3015,3203,3367,3968,4062,4251,4374,4641|5179,0:558|5180,0:684|5201,0:760|5205,0:607|5208,0:719|5210,0:581"/></pk>